{"apps":389,"games":46,"list":[{"name":"配色","icon":"https://appimg-drcn.dbankcdn.com/application/icon144/phone/b1480a5f7eab45a893a050b5746d2732.webp","category":"工具","type":"应用","releaseDate":1767704427000,"relativePath":"工具/配色.json","downCount":2531},{"name":"森果批发易","icon":"https://appimg-drcn.dbankcdn.com/application/icon144/phone/45f2bbf948b54cba8c41eb754da938ca.webp","category":"商务","type":"应用","releaseDate":1767702599000,"relativePath":"商务/森果批发易.json","downCount":3390},{"name":"你行你上","icon":"https://appimg-drcn.dbankcdn.com/application/icon144/phone/8933288f83f044d5b79f149383d285b1.webp","category":"休闲益智","type":"游戏","releaseDate":1767700340000,"relativePath":"休闲益智/你行你上.json","downCount":1019},{"name":"你行你上","icon":"https://appimg-drcn.dbankcdn.com/application/icon144/phone/8933288f83f044d5b79f149383d285b1.webp","category":"益智解谜","type":"游戏","releaseDate":1767700340000,"relativePath":"益智解谜/你行你上.json","downCount":1026},{"name":"智商不在线","icon":"https://appimg-drcn.dbankcdn.com/application/icon144/phone/fb27bef34ed74d9cac7651e95a6bc3e4.webp","category":"休闲","type":"游戏","releaseDate":1767699552000,"relativePath":"休闲/智商不在线.json","downCount":2348},{"name":"智商不在线","icon":"https://appimg-drcn.dbankcdn.com/application/icon144/phone/fb27bef34ed74d9cac7651e95a6bc3e4.webp","category":"休闲益智","type":"游戏","releaseDate":1767699552000,"relativePath":"休闲益智/智商不在线.json","downCount":1740},{"name":"译筑云","icon":"https://appimg-drcn.dbankcdn.com/application/icon144/phone/33778b782a444c26bae3c865cc234865.webp","category":"商务","type":"应用","releaseDate":1767696838000,"relativePath":"商务/译筑云.json","downCount":1142},{"name":"高精度计算器","icon":"https://appimg-drcn.dbankcdn.com/application/icon144/phone/30fcbbfefefe43fcb265bee0ec3413aa.webp","category":"工具","type":"应用","releaseDate":1767694942000,"relativePath":"工具/高精度计算器.json","downCount":1248},{"name":"通关算你牛","icon":"https://appimg-drcn.dbankcdn.com/application/icon144/phone/196f78f9e7d440bc8c9e2d045d4a5ed6.webp","category":"休闲益智","type":"游戏","releaseDate":1767692634000,"relativePath":"休闲益智/通关算你牛.json","downCount":912},{"name":"通关算你牛","icon":"https://appimg-drcn.dbankcdn.com/application/icon144/phone/196f78f9e7d440bc8c9e2d045d4a5ed6.webp","category":"策略","type":"游戏","releaseDate":1767692634000,"relativePath":"策略/通关算你牛.json","downCount":912},{"name":"通关算你牛","icon":"https://appimg-drcn.dbankcdn.com/application/icon144/phone/196f78f9e7d440bc8c9e2d045d4a5ed6.webp","category":"经营策略","type":"游戏","releaseDate":1767692634000,"relativePath":"经营策略/通关算你牛.json","downCount":912},{"name":"画画涂鸦板","icon":"https://appimg-drcn.dbankcdn.com/application/icon144/phone/7198b3e5765944ccb8491347d4bde9c6.webp","category":"艺术与设计","type":"应用","releaseDate":1767692334000,"relativePath":"艺术与设计/画画涂鸦板.json","downCount":5046},{"name":"成长轨迹","icon":"https://appimg-drcn.dbankcdn.com/application/icon144/phone/700c70d9ee4f4127ae4afd798394e99f.webp","category":"工具","type":"应用","releaseDate":1767691876000,"relativePath":"工具/成长轨迹.json","downCount":1088},{"name":"美宜佳","icon":"https://appimg-drcn.dbankcdn.com/application/icon144/phone/9514eb779cd64385ae75c24b5ac19970.webp","category":"购物","type":"应用","releaseDate":1767689485000,"relativePath":"购物/美宜佳.json","downCount":2251},{"name":"和生","icon":"https://appimg-drcn.dbankcdn.com/application/icon144/phone/58dfac5783c349459bccea850fd8f098.webp","category":"效率","type":"应用","releaseDate":1767683694000,"relativePath":"效率/和生.json","downCount":697},{"name":"交通运输共享平台","icon":"https://appimg-drcn.dbankcdn.com/application/icon144/phone/12fe617954f048ceb8c07834494da9a6.webp","category":"商务","type":"应用","releaseDate":1767681994000,"relativePath":"商务/交通运输共享平台.json","downCount":626},{"name":"经营帮","icon":"https://appimg-drcn.dbankcdn.com/application/icon144/phone/a5aee1bcf7974fbe85f63daf0f3eb289.webp","category":"商务","type":"应用","releaseDate":1767680340000,"relativePath":"商务/经营帮.json","downCount":1670},{"name":"草稿纸","icon":"https://appimg-drcn.dbankcdn.com/application/icon144/phone/5756bc18eadd416a923974d76751ba19.webp","category":"工具","type":"应用","releaseDate":1767678740000,"relativePath":"工具/草稿纸.json","downCount":19565},{"name":"百福得","icon":"https://appimg-drcn.dbankcdn.com/application/icon144/phone/1093a9bc686142ab9667ba2c4daa3db4.webp","category":"购物","type":"应用","releaseDate":1767668185000,"relativePath":"购物/百福得.json","downCount":32737},{"name":"Dazz Chic","icon":"https://appimg-drcn.dbankcdn.com/application/icon144/phone/08449df4f42044dbb1e427640b7cfb68.webp","category":"拍摄美化","type":"应用","releaseDate":1767667618000,"relativePath":"拍摄美化/Dazz Chic.json","downCount":83210},{"name":"天天台球","icon":"https://appimg-drcn.dbankcdn.com/application/icon144/phone/a47a77b1b9c14ecd8b6332b1532801ec.webp","category":"体育","type":"游戏","releaseDate":1767666936000,"relativePath":"体育/天天台球.json","downCount":184346},{"name":"天天台球","icon":"https://appimg-drcn.dbankcdn.com/application/icon144/phone/a47a77b1b9c14ecd8b6332b1532801ec.webp","category":"体育竞速","type":"游戏","releaseDate":1767666936000,"relativePath":"体育竞速/天天台球.json","downCount":156823},{"name":"安源融媒","icon":"https://appimg-drcn.dbankcdn.com/application/icon144/phone/6723c9ae4a5f4dff94b77e1725bfca5d.webp","category":"新闻","type":"应用","releaseDate":1767661857000,"relativePath":"新闻/安源融媒.json","downCount":1173},{"name":"阿基米德","icon":"https://appimg-drcn.dbankcdn.com/application/icon144/phone/a2700a019f944e97b6ea22a536334a61.webp","category":"音乐","type":"应用","releaseDate":1767661728000,"relativePath":"音乐/阿基米德.json","downCount":30440},{"name":"橙果错题本","icon":"https://appimg-drcn.dbankcdn.com/application/icon144/phone/892e9536ea954f53b1a39d86947d86e5.webp","category":"教育","type":"应用","releaseDate":1767661138000,"relativePath":"教育/橙果错题本.json","downCount":36397},{"name":"融360","icon":"https://appimg-drcn.dbankcdn.com/application/icon144/phone/0bf414faa8cc413bb017aefe7a5ab885.webp","category":"金融理财","type":"应用","releaseDate":1767621995000,"relativePath":"金融理财/融360.json","downCount":124101},{"name":"汇来米","icon":"https://appimg-drcn.dbankcdn.com/application/icon144/phone/04220b9649ab4a4485e16c2384d8055a.webp","category":"工具","type":"应用","releaseDate":1767615969000,"relativePath":"工具/汇来米.json","downCount":18041},{"name":"应急指挥","icon":"https://appimg-drcn.dbankcdn.com/application/icon144/phone/b18a63e0f8c5465d8895d1a53d66e2db.webp","category":"工具","type":"应用","releaseDate":1767613919000,"relativePath":"工具/应急指挥.json","downCount":861},{"name":"吉他谱","icon":"https://appimg-drcn.dbankcdn.com/application/icon144/phone/84ae1ee737294ff286b1bc82e219ace9.webp","category":"音乐","type":"应用","releaseDate":1767606869000,"relativePath":"音乐/吉他谱.json","downCount":5937},{"name":"约苗","icon":"https://appimg-drcn.dbankcdn.com/application/icon144/phone/bf1ced2ecc3b4c919a875fc975b61733.webp","category":"医疗","type":"应用","releaseDate":1767605776000,"relativePath":"医疗/约苗.json","downCount":15360},{"name":"Union Authenticator","icon":"https://appimg-drcn.dbankcdn.com/application/icon144/phone/52e8153470404174af752c65533b3c67.webp","category":"工具","type":"应用","releaseDate":1767602757000,"relativePath":"工具/Union Authenticator.json","downCount":2258},{"name":"携简","icon":"https://appimg-drcn.dbankcdn.com/application/icon144/phone/988bd79150504648b5c6eb6dfef029a1.webp","category":"商务","type":"应用","releaseDate":1767600584000,"relativePath":"商务/携简.json","downCount":1248},{"name":"紫金天风期货","icon":"https://appimg-drcn.dbankcdn.com/application/icon144/phone/09b4c912c37a499e820313d7bc54db9f.webp","category":"金融理财","type":"应用","releaseDate":1767595924000,"relativePath":"金融理财/紫金天风期货.json","downCount":1326},{"name":"HW CloudLink","icon":"https://appimg-drcn.dbankcdn.com/application/icon144/phone/2bb74043d3c642b8a2c598b765e9cbc5.webp","category":"商务","type":"应用","releaseDate":1767595096000,"relativePath":"商务/HW CloudLink.json","downCount":7316},{"name":"桂聘","icon":"https://appimg-drcn.dbankcdn.com/application/icon144/phone/a9a58c21dbde4e1e9af7d90e4f610ab1.webp","category":"商务","type":"应用","releaseDate":1767594905000,"relativePath":"商务/桂聘.json","downCount":4871},{"name":"Face Location","icon":"https://appimg-drcn.dbankcdn.com/application/icon144/phone/a0d6e32bb9c14d6aa3324cf01380ce8b.webp","category":"工具","type":"应用","releaseDate":1767594637000,"relativePath":"工具/Face Location.json","downCount":13691},{"name":"躺平赚大钱","icon":"https://appimg-drcn.dbankcdn.com/application/icon144/phone/1c9885d7df1b4f6c8cccbd6b653277e5.webp","category":"休闲益智","type":"游戏","releaseDate":1767593954000,"relativePath":"休闲益智/躺平赚大钱.json","downCount":23140},{"name":"怀旧模拟器","icon":"https://appimg-drcn.dbankcdn.com/application/icon144/phone/c6dcc34b9c0f49e5ae24d7ff15c8c4a9.webp","category":"工具","type":"应用","releaseDate":1767593913000,"relativePath":"工具/怀旧模拟器.json","downCount":111143},{"name":"脑洞消消消","icon":"https://appimg-drcn.dbankcdn.com/application/icon144/phone/d5689f681c474205939f7935aa2bf826.webp","category":"休闲","type":"游戏","releaseDate":1767593006000,"relativePath":"休闲/脑洞消消消.json","downCount":594},{"name":"脑洞消消消","icon":"https://appimg-drcn.dbankcdn.com/application/icon144/phone/d5689f681c474205939f7935aa2bf826.webp","category":"休闲益智","type":"游戏","releaseDate":1767593006000,"relativePath":"休闲益智/脑洞消消消.json","downCount":594},{"name":"疗愈工坊","icon":"https://appimg-drcn.dbankcdn.com/application/icon144/phone/cc4696e30fb64246a6f2258976cc069d.webp","category":"休闲益智","type":"游戏","releaseDate":1767592202000,"relativePath":"休闲益智/疗愈工坊.json","downCount":4887},{"name":"吃药打卡","icon":"https://appimg-drcn.dbankcdn.com/application/icon144/phone/2fd604a0d4174522b4ea314e4c648cc1.webp","category":"运动健康","type":"应用","releaseDate":1767585579000,"relativePath":"运动健康/吃药打卡.json","downCount":2328},{"name":"不怕你找茬","icon":"https://appimg-drcn.dbankcdn.com/application/icon144/phone/c22fd2cfd04843c29f4c1b9bc03ba3ea.webp","category":"休闲益智","type":"游戏","releaseDate":1767584700000,"relativePath":"休闲益智/不怕你找茬.json","downCount":5387},{"name":"不怕你找茬","icon":"https://appimg-drcn.dbankcdn.com/application/icon144/phone/c22fd2cfd04843c29f4c1b9bc03ba3ea.webp","category":"益智解谜","type":"游戏","releaseDate":1767584700000,"relativePath":"益智解谜/不怕你找茬.json","downCount":5423},{"name":"一起躲猫猫","icon":"https://appimg-drcn.dbankcdn.com/application/icon144/phone/22ef06e490aa4c14ade4f94c6b4ed88d.webp","category":"休闲益智","type":"游戏","releaseDate":1767584383000,"relativePath":"休闲益智/一起躲猫猫.json","downCount":11714},{"name":"一起躲猫猫","icon":"https://appimg-drcn.dbankcdn.com/application/icon144/phone/22ef06e490aa4c14ade4f94c6b4ed88d.webp","category":"棋牌桌游","type":"游戏","releaseDate":1767584383000,"relativePath":"棋牌桌游/一起躲猫猫.json","downCount":11801},{"name":"一起躲猫猫","icon":"https://appimg-drcn.dbankcdn.com/application/icon144/phone/22ef06e490aa4c14ade4f94c6b4ed88d.webp","category":"派对游戏","type":"游戏","releaseDate":1767584383000,"relativePath":"派对游戏/一起躲猫猫.json","downCount":13251},{"name":"我勒个豆","icon":"https://appimg-drcn.dbankcdn.com/application/icon144/phone/689fe689fdb346f2a81150398f4dc973.webp","category":"休闲","type":"游戏","releaseDate":1767582153000,"relativePath":"休闲/我勒个豆.json","downCount":7617},{"name":"我勒个豆","icon":"https://appimg-drcn.dbankcdn.com/application/icon144/phone/689fe689fdb346f2a81150398f4dc973.webp","category":"休闲益智","type":"游戏","releaseDate":1767582153000,"relativePath":"休闲益智/我勒个豆.json","downCount":7320},{"name":"迷你战舰","icon":"https://appimg-drcn.dbankcdn.com/application/icon144/phone/4a781eae962e4f8c8f15840b6f206f6b.webp","category":"休闲益智","type":"游戏","releaseDate":1767579052000,"relativePath":"休闲益智/迷你战舰.json","downCount":10173},{"name":"迷你战舰","icon":"https://appimg-drcn.dbankcdn.com/application/icon144/phone/4a781eae962e4f8c8f15840b6f206f6b.webp","category":"体育竞速","type":"游戏","releaseDate":1767579052000,"relativePath":"体育竞速/迷你战舰.json","downCount":10259},{"name":"易哈佛","icon":"https://appimg-drcn.dbankcdn.com/application/icon144/phone/804e89e7264a45bfbeca6e204dd9dc92.webp","category":"教育","type":"应用","releaseDate":1767578505000,"relativePath":"教育/易哈佛.json","downCount":82808},{"name":"云端学习","icon":"https://appimg-drcn.dbankcdn.com/application/icon144/phone/bbff79d73f7a4255b8f6be163d388247.webp","category":"教育","type":"应用","releaseDate":1767576200000,"relativePath":"教育/云端学习.json","downCount":93653},{"name":"肝胆相照专家版","icon":"https://appimg-drcn.dbankcdn.com/application/icon144/phone/ac0b643b81344a1cb18f00658b32775a.webp","category":"医疗","type":"应用","releaseDate":1767574027000,"relativePath":"医疗/肝胆相照专家版.json","downCount":1552},{"name":"香山智联","icon":"https://appimg-drcn.dbankcdn.com/application/icon144/phone/5875e28f2e1a43aca27c4aea2df5d326.webp","category":"运动健康","type":"应用","releaseDate":1767515491000,"relativePath":"运动健康/香山智联.json","downCount":33362},{"name":"轻卡图","icon":"https://appimg-drcn.dbankcdn.com/application/icon144/phone/9762c3735ef8445badcc8c6f73c0b087.webp","category":"拍摄美化","type":"应用","releaseDate":1767513466000,"relativePath":"拍摄美化/轻卡图.json","downCount":17073},{"name":"8848汽车学苑","icon":"https://appimg-drcn.dbankcdn.com/application/icon144/phone/39d0430361a94b6fa034fe83445de361.webp","category":"汽车","type":"应用","releaseDate":1767512417000,"relativePath":"汽车/8848汽车学苑.json","downCount":866},{"name":"汽车之家","icon":"https://appimg-drcn.dbankcdn.com/application/icon144/phone/dc34f54ff74a4d7b8b45695d7f42eeec.webp","category":"新闻","type":"应用","releaseDate":1767509457000,"relativePath":"新闻/汽车之家.json","downCount":3647581},{"name":"保安员超题库","icon":"https://appimg-drcn.dbankcdn.com/application/icon144/phone/60c7190611f7436a846cfe7cabaa89fd.webp","category":"教育","type":"应用","releaseDate":1767507144000,"relativePath":"教育/保安员超题库.json","downCount":811},{"name":"叉车司机超题库","icon":"https://appimg-drcn.dbankcdn.com/application/icon144/phone/b229f961df9549cea88e64533b13dc69.webp","category":"教育","type":"应用","releaseDate":1767506728000,"relativePath":"教育/叉车司机超题库.json","downCount":540},{"name":"玲珑密保锁","icon":"https://appimg-drcn.dbankcdn.com/application/icon144/phone/2527d77c6b0a4097a7ef1d4ecd9c6a9e.webp","category":"工具","type":"应用","releaseDate":1767506162000,"relativePath":"工具/玲珑密保锁.json","downCount":42409},{"name":"执业药师超题库","icon":"https://appimg-drcn.dbankcdn.com/application/icon144/phone/0bbbf6d7d21247e987cb9e81f6388c8e.webp","category":"教育","type":"应用","releaseDate":1767495368000,"relativePath":"教育/执业药师超题库.json","downCount":654},{"name":"保育员超题库","icon":"https://appimg-drcn.dbankcdn.com/application/icon144/phone/16aee0fa4d7444d997b3c3bd982f15ab.webp","category":"教育","type":"应用","releaseDate":1767493694000,"relativePath":"教育/保育员超题库.json","downCount":735},{"name":"医疗救护员超题库","icon":"https://appimg-drcn.dbankcdn.com/application/icon144/phone/faf5ca70e0ff45d5bb335f32fdc8e3ee.webp","category":"教育","type":"应用","releaseDate":1767493581000,"relativePath":"教育/医疗救护员超题库.json","downCount":623},{"name":"捷安特骑行","icon":"https://appimg-drcn.dbankcdn.com/application/icon144/phone/8dbb97e5e05f42debde0e79a23fc877f.webp","category":"运动健康","type":"应用","releaseDate":1767492606000,"relativePath":"运动健康/捷安特骑行.json","downCount":227277},{"name":"无人机驾驶员超题库","icon":"https://appimg-drcn.dbankcdn.com/application/icon144/phone/d943a4c468bc4028971cf47185661fb7.webp","category":"教育","type":"应用","releaseDate":1767344708000,"relativePath":"教育/无人机驾驶员超题库.json","downCount":908},{"name":"莱西信息港","icon":"https://appimg-drcn.dbankcdn.com/application/icon144/phone/bab88479d30b4f60a12f21cba23b6eff.webp","category":"生活服务","type":"应用","releaseDate":1767343130000,"relativePath":"生活服务/莱西信息港.json","downCount":1255},{"name":"平度信息港","icon":"https://appimg-drcn.dbankcdn.com/application/icon144/phone/531d540bd31f44f7a55dafa3379355e2.webp","category":"社交","type":"应用","releaseDate":1767326137000,"relativePath":"社交/平度信息港.json","downCount":1179},{"name":"巨潮资讯","icon":"https://appimg-drcn.dbankcdn.com/application/icon144/phone/82b0c47eae964bf2bbce73311fbeb0fc.webp","category":"资讯","type":"应用","releaseDate":1767266790000,"relativePath":"资讯/巨潮资讯.json","downCount":49576},{"name":"墨记日记","icon":"https://appimg-drcn.dbankcdn.com/application/icon144/phone/0cf6908d9c2d4cb9b08070890b69ed60.webp","category":"商务","type":"应用","releaseDate":1767266037000,"relativePath":"商务/墨记日记.json","downCount":62598},{"name":"骨科医院挂号网","icon":"https://appimg-drcn.dbankcdn.com/application/icon144/phone/bb1c41d0c81d41aa9646dbe7ba711e20.webp","category":"医疗","type":"应用","releaseDate":1767263253000,"relativePath":"医疗/骨科医院挂号网.json","downCount":723},{"name":"口腔科医院挂号网","icon":"https://appimg-drcn.dbankcdn.com/application/icon144/phone/f2c564ab263e4e41ae7db03f4d49932d.webp","category":"医疗","type":"应用","releaseDate":1767262487000,"relativePath":"医疗/口腔科医院挂号网.json","downCount":1399},{"name":"流水思考","icon":"https://appimg-drcn.dbankcdn.com/application/icon144/phone/189c04183e6b4e3a878e42c207398996.webp","category":"工具","type":"应用","releaseDate":1767258139000,"relativePath":"工具/流水思考.json","downCount":2083},{"name":"美络一家人","icon":"https://appimg-drcn.dbankcdn.com/application/icon144/phone/e8f36093f395432f828d9aaafbfda4aa.webp","category":"商务","type":"应用","releaseDate":1767257741000,"relativePath":"商务/美络一家人.json","downCount":930},{"name":"国信移动办公","icon":"https://appimg-drcn.dbankcdn.com/application/icon144/phone/fda80435602f49beb76685efeddfb92a.webp","category":"商务","type":"应用","releaseDate":1767252501000,"relativePath":"商务/国信移动办公.json","downCount":1961},{"name":"上海普陀","icon":"https://appimg-drcn.dbankcdn.com/application/icon144/phone/09a7100a5e114857a0d9d09012f1fe9a.webp","category":"新闻","type":"应用","releaseDate":1767252175000,"relativePath":"新闻/上海普陀.json","downCount":1471},{"name":"片刻","icon":"https://appimg-drcn.dbankcdn.com/application/icon144/phone/e99d1027f79247679542bb97439a8533.webp","category":"工具","type":"应用","releaseDate":1767248272000,"relativePath":"工具/片刻.json","downCount":725},{"name":"银河期货开户交易","icon":"https://appimg-drcn.dbankcdn.com/application/icon144/phone/fea1ec1e2ded414a85597a2cd2b895fb.webp","category":"金融理财","type":"应用","releaseDate":1767246777000,"relativePath":"金融理财/银河期货开户交易.json","downCount":8580},{"name":"智谷云办公","icon":"https://appimg-drcn.dbankcdn.com/application/icon144/phone/20ace44a0a864290ae83c0d84965545b.webp","category":"商务","type":"应用","releaseDate":1767242461000,"relativePath":"商务/智谷云办公.json","downCount":617},{"name":"极致办公","icon":"https://appimg-drcn.dbankcdn.com/application/icon144/phone/206a8eef71094fa88938fa64ff10c5dc.webp","category":"商务","type":"应用","releaseDate":1767236137000,"relativePath":"商务/极致办公.json","downCount":3068},{"name":"脸猫","icon":"https://appimg-drcn.dbankcdn.com/application/icon144/phone/881026856f8c4b98a27a08fe6192c3a6.webp","category":"拍摄美化","type":"应用","releaseDate":1767236007000,"relativePath":"拍摄美化/脸猫.json","downCount":11764},{"name":"悟东","icon":"https://appimg-drcn.dbankcdn.com/application/icon144/phone/7f257c313a8f4ca9a841d9d12e39dc19.webp","category":"工具","type":"应用","releaseDate":1767233788000,"relativePath":"工具/悟东.json","downCount":877},{"name":"当当","icon":"https://appimg-drcn.dbankcdn.com/application/icon144/phone/1e5a5dc28c1d4181837a05eedd3605ee.webp","category":"购物","type":"应用","releaseDate":1767230694000,"relativePath":"购物/当当.json","downCount":783702},{"name":"小依","icon":"https://appimg-drcn.dbankcdn.com/application/icon144/phone/c83e1aae6a524829b21543bd18522afe.webp","category":"生活服务","type":"应用","releaseDate":1767229575000,"relativePath":"生活服务/小依.json","downCount":5104},{"name":"摇一摇精灵","icon":"https://appimg-drcn.dbankcdn.com/application/icon144/phone/df397af70a2847709c298f13bcc300f7.webp","category":"工具","type":"应用","releaseDate":1767228407000,"relativePath":"工具/摇一摇精灵.json","downCount":654},{"name":"定时一键截图","icon":"https://appimg-drcn.dbankcdn.com/application/icon144/phone/00189944cff04bf5a635f5868bcdffd4.webp","category":"工具","type":"应用","releaseDate":1767181045000,"relativePath":"工具/定时一键截图.json","downCount":829},{"name":"屏幕点击录制器","icon":"https://appimg-drcn.dbankcdn.com/application/icon144/phone/b15081d22e164a0c8352fcefb66b34dd.webp","category":"工具","type":"应用","releaseDate":1767180050000,"relativePath":"工具/屏幕点击录制器.json","downCount":1357},{"name":"流浪潮汐","icon":"https://appimg-drcn.dbankcdn.com/application/icon144/phone/789409f5debc4c968b7b2b6bbb45bcb1.webp","category":"生活服务","type":"应用","releaseDate":1767177006000,"relativePath":"生活服务/流浪潮汐.json","downCount":17112},{"name":"云建宝-工人端","icon":"https://appimg-drcn.dbankcdn.com/application/icon144/phone/3810059cb5624ea5b2db4cd3f5c9c03a.webp","category":"商务","type":"应用","releaseDate":1767174436000,"relativePath":"商务/云建宝-工人端.json","downCount":11520},{"name":"潮汐表","icon":"https://appimg-drcn.dbankcdn.com/application/icon144/phone/ad9cb88c55ae46aa9a48095cd75132d2.webp","category":"生活服务","type":"应用","releaseDate":1767172533000,"relativePath":"生活服务/潮汐表.json","downCount":24579},{"name":"帮她报恩","icon":"https://appimg-drcn.dbankcdn.com/application/icon144/phone/53fb032ca216492e8c5d0165c72687fa.webp","category":"休闲益智","type":"游戏","releaseDate":1767171420000,"relativePath":"休闲益智/帮她报恩.json","downCount":864},{"name":"帮她报恩","icon":"https://appimg-drcn.dbankcdn.com/application/icon144/phone/53fb032ca216492e8c5d0165c72687fa.webp","category":"益智解谜","type":"游戏","releaseDate":1767171420000,"relativePath":"益智解谜/帮她报恩.json","downCount":919},{"name":"设备云售后","icon":"https://appimg-drcn.dbankcdn.com/application/icon144/phone/375419e2984648219d0d31ba742d412b.webp","category":"商务","type":"应用","releaseDate":1767170902000,"relativePath":"商务/设备云售后.json","downCount":604},{"name":"蓝海银行","icon":"https://appimg-drcn.dbankcdn.com/application/icon144/phone/3751ecf36aad4ce09f3d0baa4068826c.webp","category":"金融理财","type":"应用","releaseDate":1767170884000,"relativePath":"金融理财/蓝海银行.json","downCount":10594},{"name":"开心打卡","icon":"https://appimg-drcn.dbankcdn.com/application/icon144/phone/750676a843c749239d1e3b2dcb78eb36.webp","category":"生活服务","type":"应用","releaseDate":1767169181000,"relativePath":"生活服务/开心打卡.json","downCount":891},{"name":"动作录制器","icon":"https://appimg-drcn.dbankcdn.com/application/icon144/phone/6478f1dcea3e4cffa333f34e6a327262.webp","category":"工具","type":"应用","releaseDate":1767168642000,"relativePath":"工具/动作录制器.json","downCount":3948},{"name":"记事本备忘","icon":"https://appimg-drcn.dbankcdn.com/application/icon144/phone/ef856855582f459689b24c55eb0f6bd0.webp","category":"工具","type":"应用","releaseDate":1767166671000,"relativePath":"工具/记事本备忘.json","downCount":2996},{"name":"4398游戏盒","icon":"https://appimg-drcn.dbankcdn.com/application/icon144/phone/751efb1affa248e48296d9c845af28e9.webp","category":"工具","type":"应用","releaseDate":1767166129000,"relativePath":"工具/4398游戏盒.json","downCount":12541},{"name":"OnePPT","icon":"https://appimg-drcn.dbankcdn.com/application/icon144/phone/70832d585ff34d8699d3ba5843988172.webp","category":"工具","type":"应用","releaseDate":1767164608000,"relativePath":"工具/OnePPT.json","downCount":3069},{"name":"正则过滤器","icon":"https://appimg-drcn.dbankcdn.com/application/icon144/phone/1e4ae042048d4c3a94d6b124fda2e1e5.webp","category":"工具","type":"应用","releaseDate":1767162726000,"relativePath":"工具/正则过滤器.json","downCount":965},{"name":"AI全能写作","icon":"https://appimg-drcn.dbankcdn.com/application/icon144/phone/030c40680fca4956807f224be0b48983.webp","category":"工具","type":"应用","releaseDate":1767161545000,"relativePath":"工具/AI全能写作.json","downCount":5518},{"name":"掌上宏源","icon":"https://appimg-drcn.dbankcdn.com/application/icon144/phone/523d6a62bbb74f738ec462bcfd1aa840.webp","category":"金融理财","type":"应用","releaseDate":1767161471000,"relativePath":"金融理财/掌上宏源.json","downCount":6471},{"name":"墨有引力","icon":"https://appimg-drcn.dbankcdn.com/application/icon144/phone/f4127ac249d34d0389558b641060025a.webp","category":"工具","type":"应用","releaseDate":1767160445000,"relativePath":"工具/墨有引力.json","downCount":132114},{"name":"番茄轻断食","icon":"https://appimg-drcn.dbankcdn.com/application/icon144/phone/5d543a7e65bf4e21a04d329efe44c09f.webp","category":"运动健康","type":"应用","releaseDate":1767150746000,"relativePath":"运动健康/番茄轻断食.json","downCount":10676},{"name":"西瓜写作","icon":"https://appimg-drcn.dbankcdn.com/application/icon144/phone/c36cb3c90a9143f5bf6425aaa9538e98.webp","category":"工具","type":"应用","releaseDate":1767149981000,"relativePath":"工具/西瓜写作.json","downCount":955},{"name":"AI公文助手","icon":"https://appimg-drcn.dbankcdn.com/application/icon144/phone/28bb44f2951a468d81c37b298e3e07db.webp","category":"商务","type":"应用","releaseDate":1767148370000,"relativePath":"商务/AI公文助手.json","downCount":1723},{"name":"小福媒","icon":"https://appimg-drcn.dbankcdn.com/application/icon144/phone/dc15edfc6a4a429f86b97e6b201e23a8.webp","category":"社交","type":"应用","releaseDate":1767147214000,"relativePath":"社交/小福媒.json","downCount":2703},{"name":"超级流量监控","icon":"https://appimg-drcn.dbankcdn.com/application/icon144/phone/3aad098680e6404c98c55e7f22e2fbea.webp","category":"工具","type":"应用","releaseDate":1767146287000,"relativePath":"工具/超级流量监控.json","downCount":1183},{"name":"AI智能写作","icon":"https://appimg-drcn.dbankcdn.com/application/icon144/phone/51a483955fa8478db342467760469b93.webp","category":"工具","type":"应用","releaseDate":1767145934000,"relativePath":"工具/AI智能写作.json","downCount":30561},{"name":"长安Topspace","icon":"https://appimg-drcn.dbankcdn.com/application/icon144/phone/b8c39fca1e3a48708357c508b433e78d.webp","category":"汽车","type":"应用","releaseDate":1767144976000,"relativePath":"汽车/长安Topspace.json","downCount":10355},{"name":"超级课程表","icon":"https://appimg-drcn.dbankcdn.com/application/icon144/phone/a0d7a30fa4d849c2890a3fc801a56d76.webp","category":"教育","type":"应用","releaseDate":1767098395000,"relativePath":"教育/超级课程表.json","downCount":185230},{"name":"东海通","icon":"https://appimg-drcn.dbankcdn.com/application/icon144/phone/66310159ad374ca4b946b2a7dd20c43e.webp","category":"金融理财","type":"应用","releaseDate":1767096711000,"relativePath":"金融理财/东海通.json","downCount":31198},{"name":"批量输入助手","icon":"https://appimg-drcn.dbankcdn.com/application/icon144/phone/882ed2a9ac6a44fba3601ec7853dfce8.webp","category":"工具","type":"应用","releaseDate":1767096172000,"relativePath":"工具/批量输入助手.json","downCount":644},{"name":"V站","icon":"https://appimg-drcn.dbankcdn.com/application/icon144/phone/d470097347cb4ad599438dd702973dba.webp","category":"体育","type":"应用","releaseDate":1767093961000,"relativePath":"体育/V站.json","downCount":5802},{"name":"配音专家","icon":"https://appimg-drcn.dbankcdn.com/application/icon144/phone/cc2fba7f354642e89ac38fd72f52ab45.webp","category":"工具","type":"应用","releaseDate":1767093363000,"relativePath":"工具/配音专家.json","downCount":2603},{"name":"铱云易订货","icon":"https://appimg-drcn.dbankcdn.com/application/icon144/phone/32ccdcfc4d4a4de28d988dc367b1b2e2.webp","category":"购物","type":"应用","releaseDate":1767091456000,"relativePath":"购物/铱云易订货.json","downCount":6914},{"name":"WiFi密码查看助手","icon":"https://appimg-drcn.dbankcdn.com/application/icon144/phone/941ea74981594a2486d3b349c62bf465.webp","category":"工具","type":"应用","releaseDate":1767084965000,"relativePath":"工具/WiFi密码查看助手.json","downCount":48394},{"name":"全球家精选","icon":"https://appimg-drcn.dbankcdn.com/application/icon144/phone/5daf978e4dcf4ac0843a447daf2c8b42.webp","category":"购物","type":"应用","releaseDate":1767082576000,"relativePath":"购物/全球家精选.json","downCount":4298},{"name":"及象乐园","icon":"https://appimg-drcn.dbankcdn.com/application/icon144/phone/05f44580bc8c48d0bf323d315b07c11d.webp","category":"教育","type":"应用","releaseDate":1767081597000,"relativePath":"教育/及象乐园.json","downCount":1146},{"name":"源点资讯","icon":"https://appimg-drcn.dbankcdn.com/application/icon144/phone/24a54515626947c1bfda36e23e8a40f3.webp","category":"金融理财","type":"应用","releaseDate":1767079189000,"relativePath":"金融理财/源点资讯.json","downCount":760},{"name":"定位模拟相机","icon":"https://appimg-drcn.dbankcdn.com/application/icon144/phone/4a99dcf293ac483eb6520332cfc17da4.webp","category":"拍摄美化","type":"应用","releaseDate":1767079128000,"relativePath":"拍摄美化/定位模拟相机.json","downCount":888},{"name":"爱传","icon":"https://appimg-drcn.dbankcdn.com/application/icon144/phone/a7e599db991c40be87c1c0b31865c220.webp","category":"社交","type":"应用","releaseDate":1767077089000,"relativePath":"社交/爱传.json","downCount":1126},{"name":"钛媒体","icon":"https://appimg-drcn.dbankcdn.com/application/icon144/phone/ec0c110a7d7043d4a3a62af73f450caf.webp","category":"资讯","type":"应用","releaseDate":1767075141000,"relativePath":"资讯/钛媒体.json","downCount":17539},{"name":"壁纸秀","icon":"https://appimg-drcn.dbankcdn.com/application/icon144/phone/bd9d3ad7f7564c319d9dacd42c3cb33d.webp","category":"主题","type":"应用","releaseDate":1767074476000,"relativePath":"主题/壁纸秀.json","downCount":3374},{"name":"智慧记星火","icon":"https://appimg-drcn.dbankcdn.com/application/icon144/phone/60de88c8d84f490188e4802401f8cade.webp","category":"商务","type":"应用","releaseDate":1767065835000,"relativePath":"商务/智慧记星火.json","downCount":4147},{"name":"三立博易大师","icon":"https://appimg-drcn.dbankcdn.com/application/icon144/phone/005c024cea5b4efcbc8d6df5a81a6323.webp","category":"金融理财","type":"应用","releaseDate":1767063339000,"relativePath":"金融理财/三立博易大师.json","downCount":2793},{"name":"拓课云Plus","icon":"https://appimg-drcn.dbankcdn.com/application/icon144/phone/f7eea3e4dac74a8e8609778b43eeffab.webp","category":"工具","type":"应用","releaseDate":1767063185000,"relativePath":"工具/拓课云Plus.json","downCount":4888},{"name":"定时自动触发器","icon":"https://appimg-drcn.dbankcdn.com/application/icon144/phone/e4c00d186d074b6b96cfae7dfdc16dd2.webp","category":"工具","type":"应用","releaseDate":1767063143000,"relativePath":"工具/定时自动触发器.json","downCount":1205},{"name":"秒闪去水印","icon":"https://appimg-drcn.dbankcdn.com/application/icon144/phone/59d2436e2cae4c34acbc90f47ee53cf2.webp","category":"拍摄美化","type":"应用","releaseDate":1767059883000,"relativePath":"拍摄美化/秒闪去水印.json","downCount":10413},{"name":"北京儿童医院保定医院","icon":"https://appimg-drcn.dbankcdn.com/application/icon144/phone/6e59a8c5221e4eefbdec25baa0065968.webp","category":"工具","type":"应用","releaseDate":1767059776000,"relativePath":"工具/北京儿童医院保定医院.json","downCount":18976},{"name":"郑商所综合服务App","icon":"https://appimg-drcn.dbankcdn.com/application/icon144/phone/6962cf231d894133b029a4b8cc3280ec.webp","category":"金融理财","type":"应用","releaseDate":1767058345000,"relativePath":"金融理财/郑商所综合服务App.json","downCount":1278},{"name":"ShowPattern","icon":"https://appimg-drcn.dbankcdn.com/application/icon144/phone/ccd254aeb2814db5926d2cf67fd1af1b.webp","category":"工具","type":"应用","releaseDate":1767055996000,"relativePath":"工具/ShowPattern.json","downCount":883},{"name":"凯叔讲故事","icon":"https://appimg-drcn.dbankcdn.com/application/icon144/phone/fdad6b6b57c54d68a2d7a7d379fd0df6.webp","category":"阅读与工具书","type":"应用","releaseDate":1767013681000,"relativePath":"阅读与工具书/凯叔讲故事.json","downCount":798055},{"name":"adb文件传输","icon":"https://appimg-drcn.dbankcdn.com/application/icon144/phone/5bb7532bd7e14c8ba194ce65367f62d2.webp","category":"工具","type":"应用","releaseDate":1767013572000,"relativePath":"工具/adb文件传输.json","downCount":1319},{"name":"云商店","icon":"https://appimg-drcn.dbankcdn.com/application/icon144/phone/f5f87402223c406088ac6698fedaf098.webp","category":"商务","type":"应用","releaseDate":1767011223000,"relativePath":"商务/云商店.json","downCount":5692},{"name":"一键批量重命名","icon":"https://appimg-drcn.dbankcdn.com/application/icon144/phone/9aa05812ddf24f9884dd7d46c2a27e0a.webp","category":"工具","type":"应用","releaseDate":1767011154000,"relativePath":"工具/一键批量重命名.json","downCount":863},{"name":"央视影音","icon":"https://appimg-drcn.dbankcdn.com/application/icon144/phone/c88fd3ff4e3549a28cc57e7e30cff664.webp","category":"影视与直播","type":"应用","releaseDate":1767010351000,"relativePath":"影视与直播/央视影音.json","downCount":1529442},{"name":"轻糖","icon":"https://appimg-drcn.dbankcdn.com/application/icon144/phone/109f9e8fb19e4019be0f6e28bf50b2f4.webp","category":"社交","type":"应用","releaseDate":1767008485000,"relativePath":"社交/轻糖.json","downCount":15027},{"name":"维迈通多多","icon":"https://appimg-drcn.dbankcdn.com/application/icon144/phone/5f843b79710544b3a02247bd88857e98.webp","category":"工具","type":"应用","releaseDate":1767006951000,"relativePath":"工具/维迈通多多.json","downCount":90686},{"name":"流荧拾刻","icon":"https://appimg-drcn.dbankcdn.com/application/icon144/phone/90b95377252642f28ad8087cb2394d6b.webp","category":"拍摄美化","type":"应用","releaseDate":1767002672000,"relativePath":"拍摄美化/流荧拾刻.json","downCount":999},{"name":"思续","icon":"https://appimg-drcn.dbankcdn.com/application/icon144/phone/bb9cc41fed854fed8d72f5165c810c2f.webp","category":"效率","type":"应用","releaseDate":1766999393000,"relativePath":"效率/思续.json","downCount":2697},{"name":"医信平台端","icon":"https://appimg-drcn.dbankcdn.com/application/icon144/phone/53d8eba0178241e1bcaf1a49f0476f5f.webp","category":"医疗","type":"应用","releaseDate":1766999071000,"relativePath":"医疗/医信平台端.json","downCount":1774},{"name":"永升活","icon":"https://appimg-drcn.dbankcdn.com/application/icon144/phone/d779cc4bc1444eeabb322c69bac1c15c.webp","category":"生活服务","type":"应用","releaseDate":1766998716000,"relativePath":"生活服务/永升活.json","downCount":44162},{"name":"财达博易app","icon":"https://appimg-drcn.dbankcdn.com/application/icon144/phone/49accf47246449a8a7b14c890995bbd3.webp","category":"金融理财","type":"应用","releaseDate":1766998284000,"relativePath":"金融理财/财达博易app.json","downCount":2160},{"name":"卡林巴拇指琴","icon":"https://appimg-drcn.dbankcdn.com/application/icon144/phone/ff26d1f26e5e4e5198169b83acbe0826.webp","category":"音乐","type":"应用","releaseDate":1766997734000,"relativePath":"音乐/卡林巴拇指琴.json","downCount":3345},{"name":"赣州银行企业手机银行","icon":"https://appimg-drcn.dbankcdn.com/application/icon144/phone/c3f0905e7d8a4576942ff80b22bf373a.webp","category":"金融理财","type":"应用","releaseDate":1766996502000,"relativePath":"金融理财/赣州银行企业手机银行.json","downCount":1693},{"name":"金石期货","icon":"https://appimg-drcn.dbankcdn.com/application/icon144/phone/6c872f6e318645558a87bde1865a1717.webp","category":"金融理财","type":"应用","releaseDate":1766994584000,"relativePath":"金融理财/金石期货.json","downCount":1582},{"name":"手机备份助手","icon":"https://appimg-drcn.dbankcdn.com/application/icon144/phone/c1766c5f5fae484dae3484f320b407b1.webp","category":"工具","type":"应用","releaseDate":1766992242000,"relativePath":"工具/手机备份助手.json","downCount":10958},{"name":"蔚来校园","icon":"https://appimg-drcn.dbankcdn.com/application/icon144/phone/ea219fad68a9451ca1d6270579828dca.webp","category":"生活服务","type":"应用","releaseDate":1766990852000,"relativePath":"生活服务/蔚来校园.json","downCount":11268},{"name":"远程复制粘贴","icon":"https://appimg-drcn.dbankcdn.com/application/icon144/phone/31a64ed3644d475a80fc7bbb62eaa2b9.webp","category":"工具","type":"应用","releaseDate":1766990067000,"relativePath":"工具/远程复制粘贴.json","downCount":535},{"name":"网上国网","icon":"https://appimg-drcn.dbankcdn.com/application/icon144/phone/04e41562548d44baa3fb8997172caa75.webp","category":"生活服务","type":"应用","releaseDate":1766989456000,"relativePath":"生活服务/网上国网.json","downCount":7252437},{"name":"拍照输入助手","icon":"https://appimg-drcn.dbankcdn.com/application/icon144/phone/ef62ee6c5be74281a929951a7a43c38d.webp","category":"工具","type":"应用","releaseDate":1766895043000,"relativePath":"工具/拍照输入助手.json","downCount":647},{"name":"徕芬","icon":"https://appimg-drcn.dbankcdn.com/application/icon144/phone/5ba26b6b06fc4d1bb469af1e05d4553a.webp","category":"工具","type":"应用","releaseDate":1766836844000,"relativePath":"工具/徕芬.json","downCount":52812},{"name":"AI外教","icon":"https://appimg-drcn.dbankcdn.com/application/icon144/phone/e40e6c20c15a4dbc94da8f81354cfeb7.webp","category":"教育","type":"应用","releaseDate":1766835971000,"relativePath":"教育/AI外教.json","downCount":38905},{"name":"天目云","icon":"https://appimg-drcn.dbankcdn.com/application/icon144/phone/de6dfdc66cbe4475aa4a03246672fa22.webp","category":"工具","type":"应用","releaseDate":1766831343000,"relativePath":"工具/天目云.json","downCount":610},{"name":"Songs AI","icon":"https://appimg-drcn.dbankcdn.com/application/icon144/phone/d4d31c89f8fa41158d428c5558824c3e.webp","category":"工具","type":"应用","releaseDate":1766829291000,"relativePath":"工具/Songs AI.json","downCount":2942},{"name":"测网速UUSpeed","icon":"https://appimg-drcn.dbankcdn.com/application/icon144/phone/6ed8e0734c7d43f6915c53d04d30ad70.webp","category":"工具","type":"应用","releaseDate":1766825147000,"relativePath":"工具/测网速UUSpeed.json","downCount":433716},{"name":"移动应急","icon":"https://appimg-drcn.dbankcdn.com/application/icon144/phone/768131527939444fb2e41a4a68f039c9.webp","category":"商务","type":"应用","releaseDate":1766823371000,"relativePath":"商务/移动应急.json","downCount":41723},{"name":"融达期货","icon":"https://appimg-drcn.dbankcdn.com/application/icon144/phone/ced5055cdd924352b5c4f7e92e532388.webp","category":"金融理财","type":"应用","releaseDate":1766822952000,"relativePath":"金融理财/融达期货.json","downCount":1889},{"name":"眼科医院挂号网","icon":"https://appimg-drcn.dbankcdn.com/application/icon144/phone/7c8e223998fd4774b202a3ff113f0c21.webp","category":"医疗","type":"应用","releaseDate":1766821852000,"relativePath":"医疗/眼科医院挂号网.json","downCount":1022},{"name":"仲泰安全学习","icon":"https://appimg-drcn.dbankcdn.com/application/icon144/phone/b424a6dfbcef42b08555429284424b1e.webp","category":"教育","type":"应用","releaseDate":1766820597000,"relativePath":"教育/仲泰安全学习.json","downCount":810},{"name":"法本通","icon":"https://appimg-drcn.dbankcdn.com/application/icon144/phone/e42467d66cbf407eb08569c3a10f8a79.webp","category":"商务","type":"应用","releaseDate":1766817176000,"relativePath":"商务/法本通.json","downCount":1943},{"name":"创芯检测","icon":"https://appimg-drcn.dbankcdn.com/application/icon144/phone/2f918040781e4cdd8659c2bafd33cc4e.webp","category":"工具","type":"应用","releaseDate":1766811984000,"relativePath":"工具/创芯检测.json","downCount":7079},{"name":"PPT模板堆","icon":"https://appimg-drcn.dbankcdn.com/application/icon144/phone/60ca775cdfc74df79fcc1a5d238329d9.webp","category":"商务","type":"应用","releaseDate":1766806705000,"relativePath":"商务/PPT模板堆.json","downCount":866},{"name":"录屏截图专家","icon":"https://appimg-drcn.dbankcdn.com/application/icon144/phone/f87a0b396a7a401bb08b78318b2a9d57.webp","category":"工具","type":"应用","releaseDate":1766801918000,"relativePath":"工具/录屏截图专家.json","downCount":1381},{"name":"i上商","icon":"https://appimg-drcn.dbankcdn.com/application/icon144/phone/34b61e025e7f494dadfef65aaced0c05.webp","category":"商务","type":"应用","releaseDate":1766801005000,"relativePath":"商务/i上商.json","downCount":999},{"name":"全房通","icon":"https://appimg-drcn.dbankcdn.com/application/icon144/phone/608aa938329b448da1726aca7f2a2cc6.webp","category":"房产与装修","type":"应用","releaseDate":1766797856000,"relativePath":"房产与装修/全房通.json","downCount":5742},{"name":"中融汇信期货","icon":"https://appimg-drcn.dbankcdn.com/application/icon144/phone/c7c6039e3dc74a6089a924a3017bd17c.webp","category":"金融理财","type":"应用","releaseDate":1766797462000,"relativePath":"金融理财/中融汇信期货.json","downCount":861},{"name":"今彩萍乡","icon":"https://appimg-drcn.dbankcdn.com/application/icon144/phone/79cb9edc81f8463f91862ede261f548b.webp","category":"新闻","type":"应用","releaseDate":1766756414000,"relativePath":"新闻/今彩萍乡.json","downCount":2586},{"name":"离线图片文字识别","icon":"https://appimg-drcn.dbankcdn.com/application/icon144/phone/d7e5a76b84c54dd182de5873887c498b.webp","category":"工具","type":"应用","releaseDate":1766755616000,"relativePath":"工具/离线图片文字识别.json","downCount":796},{"name":"筑梦AI","icon":"https://appimg-drcn.dbankcdn.com/application/icon144/phone/a43b72c525d7453cba0bbc681a9c28ce.webp","category":"拍摄美化","type":"应用","releaseDate":1766755614000,"relativePath":"拍摄美化/筑梦AI.json","downCount":27932},{"name":"Make Best Music","icon":"https://appimg-drcn.dbankcdn.com/application/icon144/phone/ec3bfc3efdbd4719b682275244d48d2e.webp","category":"工具","type":"应用","releaseDate":1766755040000,"relativePath":"工具/Make Best Music.json","downCount":1785},{"name":"TineChat","icon":"https://appimg-drcn.dbankcdn.com/application/icon144/phone/0cebf14d18604156bba36e3ef6c17471.webp","category":"商务","type":"应用","releaseDate":1766750426000,"relativePath":"商务/TineChat.json","downCount":1490},{"name":"装修管家","icon":"https://appimg-drcn.dbankcdn.com/application/icon144/phone/32d602994980442bb0b4835887c73151.webp","category":"房产与装修","type":"应用","releaseDate":1766749715000,"relativePath":"房产与装修/装修管家.json","downCount":4989},{"name":"节奏达人连梗","icon":"https://appimg-drcn.dbankcdn.com/application/icon144/phone/f57db32c71064809895240dae1ab0cd1.webp","category":"休闲益智","type":"游戏","releaseDate":1766745074000,"relativePath":"休闲益智/节奏达人连梗.json","downCount":927},{"name":"节奏达人连梗","icon":"https://appimg-drcn.dbankcdn.com/application/icon144/phone/f57db32c71064809895240dae1ab0cd1.webp","category":"音乐","type":"游戏","releaseDate":1766745074000,"relativePath":"音乐/节奏达人连梗.json","downCount":1875},{"name":"答案之书智能回答","icon":"https://appimg-drcn.dbankcdn.com/application/icon144/phone/98f01ac6365d448fb40817d318e72da3.webp","category":"工具","type":"应用","releaseDate":1766743381000,"relativePath":"工具/答案之书智能回答.json","downCount":711},{"name":"一键识别图片","icon":"https://appimg-drcn.dbankcdn.com/application/icon144/phone/cd44e4e9b41a4fef920a8d3e6589b6af.webp","category":"工具","type":"应用","releaseDate":1766743278000,"relativePath":"工具/一键识别图片.json","downCount":717},{"name":"摇骰子","icon":"https://appimg-drcn.dbankcdn.com/application/icon144/phone/19b150a2420441bca4f0d8c86a76acdb.webp","category":"工具","type":"应用","releaseDate":1766742725000,"relativePath":"工具/摇骰子.json","downCount":5201},{"name":"日常小记","icon":"https://appimg-drcn.dbankcdn.com/application/icon144/phone/aa3c1acef48540359a94f74a2b4f43b8.webp","category":"效率","type":"应用","releaseDate":1766742222000,"relativePath":"效率/日常小记.json","downCount":589},{"name":"云南农机补贴","icon":"https://appimg-drcn.dbankcdn.com/application/icon144/phone/ed1d75a3d4614ed49497f4245b1fbe10.webp","category":"工具","type":"应用","releaseDate":1766741330000,"relativePath":"工具/云南农机补贴.json","downCount":2776},{"name":"装修设计软件","icon":"https://appimg-drcn.dbankcdn.com/application/icon144/phone/a2a4d48cf4344ac6ab4893d468f34915.webp","category":"房产与装修","type":"应用","releaseDate":1766738841000,"relativePath":"房产与装修/装修设计软件.json","downCount":15380},{"name":"如神AI写作","icon":"https://appimg-drcn.dbankcdn.com/application/icon144/phone/e458b68a899147728ba275b708d193c9.webp","category":"工具","type":"应用","releaseDate":1766736950000,"relativePath":"工具/如神AI写作.json","downCount":1032},{"name":"秀米XIUMI","icon":"https://appimg-drcn.dbankcdn.com/application/icon144/phone/ddcbf381417545d8a2cb59ad2ccea152.webp","category":"工具","type":"应用","releaseDate":1766735304000,"relativePath":"工具/秀米XIUMI.json","downCount":59929},{"name":"数字北大荒","icon":"https://appimg-drcn.dbankcdn.com/application/icon144/phone/4c2567a845994d26bb3548fb3f2998dd.webp","category":"工具","type":"应用","releaseDate":1766735099000,"relativePath":"工具/数字北大荒.json","downCount":6162},{"name":"金立手表","icon":"https://appimg-drcn.dbankcdn.com/application/icon144/phone/0de1a5e8c81e4f6a98f785cdf6b287b4.webp","category":"工具","type":"应用","releaseDate":1766732962000,"relativePath":"工具/金立手表.json","downCount":13102},{"name":"怪谈太阳先生","icon":"https://appimg-drcn.dbankcdn.com/application/icon144/phone/6e1a300d8880478182670b31cc2e575b.webp","category":"休闲益智","type":"游戏","releaseDate":1766732193000,"relativePath":"休闲益智/怪谈太阳先生.json","downCount":658},{"name":"怪谈太阳先生","icon":"https://appimg-drcn.dbankcdn.com/application/icon144/phone/6e1a300d8880478182670b31cc2e575b.webp","category":"益智解谜","type":"游戏","releaseDate":1766732193000,"relativePath":"益智解谜/怪谈太阳先生.json","downCount":658},{"name":"文件面对面分享","icon":"https://appimg-drcn.dbankcdn.com/application/icon144/phone/5a6ecfc797304917b1e64d946a205964.webp","category":"工具","type":"应用","releaseDate":1766731983000,"relativePath":"工具/文件面对面分享.json","downCount":1884},{"name":"普拉提运动","icon":"https://appimg-drcn.dbankcdn.com/application/icon144/phone/106822595ec14fe4ba58a7076286aaae.webp","category":"运动健康","type":"应用","releaseDate":1766731028000,"relativePath":"运动健康/普拉提运动.json","downCount":29126},{"name":"养猪宝","icon":"https://appimg-drcn.dbankcdn.com/application/icon144/phone/e3e22dca707840c2b4a46f2a00e1fa0f.webp","category":"资讯","type":"应用","releaseDate":1766723616000,"relativePath":"资讯/养猪宝.json","downCount":1827},{"name":"栢顺手机电子工票软件","icon":"https://appimg-drcn.dbankcdn.com/application/icon144/phone/6d2eeb69930a44f5b3b9a21fc5fe97dd.webp","category":"商务","type":"应用","releaseDate":1766721665000,"relativePath":"商务/栢顺手机电子工票软件.json","downCount":1377},{"name":"风华宁大","icon":"https://appimg-drcn.dbankcdn.com/application/icon144/phone/f1502d681a4843e59fedc497c1635cd4.webp","category":"商务","type":"应用","releaseDate":1766717114000,"relativePath":"商务/风华宁大.json","downCount":3435},{"name":"甘快办","icon":"https://appimg-drcn.dbankcdn.com/application/icon144/phone/4633490cfd444b6faecc5f64898d7639.webp","category":"生活服务","type":"应用","releaseDate":1766716445000,"relativePath":"生活服务/甘快办.json","downCount":213506},{"name":"交银人寿","icon":"https://appimg-drcn.dbankcdn.com/application/icon144/phone/2bc9e518ea7242d4b20d0ab7131ac914.webp","category":"金融理财","type":"应用","releaseDate":1766711841000,"relativePath":"金融理财/交银人寿.json","downCount":13500},{"name":"AI智能计算器","icon":"https://appimg-drcn.dbankcdn.com/application/icon144/phone/d25e98dce5f7439e8aa2f107d435b588.webp","category":"工具","type":"应用","releaseDate":1766711697000,"relativePath":"工具/AI智能计算器.json","downCount":1092},{"name":"盈球大师","icon":"https://appimg-drcn.dbankcdn.com/application/icon144/phone/c70eb09699ba442a8ee45f2cc5d3f151.webp","category":"体育","type":"应用","releaseDate":1766710355000,"relativePath":"体育/盈球大师.json","downCount":18260},{"name":"盲盒贴纸书","icon":"https://appimg-drcn.dbankcdn.com/application/icon144/phone/6ecae9ab0870416d9a707249282c100e.webp","category":"休闲","type":"游戏","releaseDate":1766664080000,"relativePath":"休闲/盲盒贴纸书.json","downCount":1069},{"name":"盲盒贴纸书","icon":"https://appimg-drcn.dbankcdn.com/application/icon144/phone/6ecae9ab0870416d9a707249282c100e.webp","category":"休闲益智","type":"游戏","releaseDate":1766664080000,"relativePath":"休闲益智/盲盒贴纸书.json","downCount":767},{"name":"学写字","icon":"https://appimg-drcn.dbankcdn.com/application/icon144/phone/cfa9b7a741f9457ba30b142ab6b66ffb.webp","category":"教育","type":"应用","releaseDate":1766662835000,"relativePath":"教育/学写字.json","downCount":2322},{"name":"小麦排队通","icon":"https://appimg-drcn.dbankcdn.com/application/icon144/phone/5f8563dd61e248b8a4685bc66b66d20c.webp","category":"工具","type":"应用","releaseDate":1766659152000,"relativePath":"工具/小麦排队通.json","downCount":515},{"name":"桌面记事本","icon":"https://appimg-drcn.dbankcdn.com/application/icon144/phone/fbd99a822b4b4dc2aa687eaffbfeabe4.webp","category":"工具","type":"应用","releaseDate":1766655570000,"relativePath":"工具/桌面记事本.json","downCount":3557},{"name":"升仕商城","icon":"https://appimg-drcn.dbankcdn.com/application/icon144/phone/837e9393692948e8b414b6cf94936a9c.webp","category":"汽车","type":"应用","releaseDate":1766654645000,"relativePath":"汽车/升仕商城.json","downCount":13870},{"name":"学法减分搜题酱","icon":"https://appimg-drcn.dbankcdn.com/application/icon144/phone/ce9a49884cf94a76a20d6445f4aec6d7.webp","category":"汽车","type":"应用","releaseDate":1766653824000,"relativePath":"汽车/学法减分搜题酱.json","downCount":2617},{"name":"太阳树","icon":"https://appimg-drcn.dbankcdn.com/application/icon144/phone/e0880cde3f284e27b0a16abff84ea961.webp","category":"工具","type":"应用","releaseDate":1766651896000,"relativePath":"工具/太阳树.json","downCount":9503},{"name":"中国医促会OA平台","icon":"https://appimg-drcn.dbankcdn.com/application/icon144/phone/62921399e89e4522a6bdf61cb0d29478.webp","category":"商务","type":"应用","releaseDate":1766651496000,"relativePath":"商务/中国医促会OA平台.json","downCount":837},{"name":"天工音乐AI写歌","icon":"https://appimg-drcn.dbankcdn.com/application/icon144/phone/59c14e99fe254cff8e3e438e74cfae48.webp","category":"音乐","type":"应用","releaseDate":1766650355000,"relativePath":"音乐/天工音乐AI写歌.json","downCount":5259},{"name":"智慧泉海","icon":"https://appimg-drcn.dbankcdn.com/application/icon144/phone/b22744002fe8430ebe698a922556805c.webp","category":"商务","type":"应用","releaseDate":1766648874000,"relativePath":"商务/智慧泉海.json","downCount":1359},{"name":"中国科大","icon":"https://appimg-drcn.dbankcdn.com/application/icon144/phone/e2d94be508d5456588934bb1d778d5de.webp","category":"资讯","type":"应用","releaseDate":1766648403000,"relativePath":"资讯/中国科大.json","downCount":3380},{"name":"校芜优","icon":"https://appimg-drcn.dbankcdn.com/application/icon144/phone/36c56fe13aab4dfea02d227bca818c85.webp","category":"商务","type":"应用","releaseDate":1766646120000,"relativePath":"商务/校芜优.json","downCount":650},{"name":"河北经贸大学","icon":"https://appimg-drcn.dbankcdn.com/application/icon144/phone/8aea1e1e04fa4ef5ba591cef5affad8f.webp","category":"工具","type":"应用","releaseDate":1766645612000,"relativePath":"工具/河北经贸大学.json","downCount":1608},{"name":"海聚英才通","icon":"https://appimg-drcn.dbankcdn.com/application/icon144/phone/da9ef0145c2142319411a63d0382b486.webp","category":"商务","type":"应用","releaseDate":1766632725000,"relativePath":"商务/海聚英才通.json","downCount":1150},{"name":"渝悦云护理","icon":"https://appimg-drcn.dbankcdn.com/application/icon144/phone/9845e6d4739c428da564e31d0c72d0e2.webp","category":"医疗","type":"应用","releaseDate":1766632502000,"relativePath":"医疗/渝悦云护理.json","downCount":920},{"name":"脉车人","icon":"https://appimg-drcn.dbankcdn.com/application/icon144/phone/89775ed43b044a078039bcf47ce0ef82.webp","category":"效率","type":"应用","releaseDate":1766630625000,"relativePath":"效率/脉车人.json","downCount":915},{"name":"成人高考专升本考试聚题库","icon":"https://appimg-drcn.dbankcdn.com/application/icon144/phone/451e7edcf50547e091d0e8ef5244812d.webp","category":"教育","type":"应用","releaseDate":1766630476000,"relativePath":"教育/成人高考专升本考试聚题库.json","downCount":880},{"name":"志愿山东","icon":"https://appimg-drcn.dbankcdn.com/application/icon144/phone/565c88ed9aa54c1781144209a8f4c7b4.webp","category":"生活服务","type":"应用","releaseDate":1766629409000,"relativePath":"生活服务/志愿山东.json","downCount":12913},{"name":"海博TV","icon":"https://appimg-drcn.dbankcdn.com/application/icon144/phone/672f261b1d3848c88722600a3e0ec46a.webp","category":"新闻","type":"应用","releaseDate":1766590336000,"relativePath":"新闻/海博TV.json","downCount":4007},{"name":"铁路12306","icon":"https://appimg-drcn.dbankcdn.com/application/icon144/phone/762d165d74244d479b11939080052be8.webp","category":"出行导航","type":"应用","releaseDate":1766570411000,"relativePath":"出行导航/铁路12306.json","downCount":19777345},{"name":"建造师快题库","icon":"https://appimg-drcn.dbankcdn.com/application/icon144/phone/b8aeea98fb454fb88f94349450d4f589.webp","category":"教育","type":"应用","releaseDate":1766569226000,"relativePath":"教育/建造师快题库.json","downCount":32905},{"name":"经济师快题库","icon":"https://appimg-drcn.dbankcdn.com/application/icon144/phone/6772d42732244902a8084b4a246ea792.webp","category":"教育","type":"应用","releaseDate":1766567580000,"relativePath":"教育/经济师快题库.json","downCount":19985},{"name":"伙伴云","icon":"https://appimg-drcn.dbankcdn.com/application/icon144/phone/1db0c3f1a326439ba2c9d8eb922a4b0a.webp","category":"商务","type":"应用","releaseDate":1766567219000,"relativePath":"商务/伙伴云.json","downCount":5498},{"name":"自动连播器","icon":"https://appimg-drcn.dbankcdn.com/application/icon144/phone/4174bf8e9b4d43fba923fdc407d43ef3.webp","category":"工具","type":"应用","releaseDate":1766562788000,"relativePath":"工具/自动连播器.json","downCount":922},{"name":"一级消防工程师考试聚题库","icon":"https://appimg-drcn.dbankcdn.com/application/icon144/phone/72bee3cbcee64d7e910b39a77a77099a.webp","category":"教育","type":"应用","releaseDate":1766562676000,"relativePath":"教育/一级消防工程师考试聚题库.json","downCount":629},{"name":"小日常","icon":"https://appimg-drcn.dbankcdn.com/application/icon144/phone/17aed0eccf5141daacc03e99e518d141.webp","category":"效率","type":"应用","releaseDate":1766562595000,"relativePath":"效率/小日常.json","downCount":28062},{"name":"收银审核员考试聚题库","icon":"https://appimg-drcn.dbankcdn.com/application/icon144/phone/f74d24a25fa14f5ea08c742a5a6c2944.webp","category":"教育","type":"应用","releaseDate":1766561115000,"relativePath":"教育/收银审核员考试聚题库.json","downCount":820},{"name":"房地产经纪人考试聚题库","icon":"https://appimg-drcn.dbankcdn.com/application/icon144/phone/13c5284abbfd46f1afba2ad1dedda509.webp","category":"教育","type":"应用","releaseDate":1766559115000,"relativePath":"教育/房地产经纪人考试聚题库.json","downCount":738},{"name":"出版专业资格考试聚题库","icon":"https://appimg-drcn.dbankcdn.com/application/icon144/phone/ae3d5905e4bf47fba57144159a5f6c03.webp","category":"教育","type":"应用","releaseDate":1766558637000,"relativePath":"教育/出版专业资格考试聚题库.json","downCount":530},{"name":"柠檬笔记","icon":"https://appimg-drcn.dbankcdn.com/application/icon144/phone/1067609251254c92bda3c83b5bf8262e.webp","category":"商务","type":"应用","releaseDate":1766556247000,"relativePath":"商务/柠檬笔记.json","downCount":3706},{"name":"经络养生","icon":"https://appimg-drcn.dbankcdn.com/application/icon144/phone/6a2351acc8964b93b153b12a655c317b.webp","category":"运动健康","type":"应用","releaseDate":1766555469000,"relativePath":"运动健康/经络养生.json","downCount":2785},{"name":"新博少儿","icon":"https://appimg-drcn.dbankcdn.com/application/icon144/phone/41b81ae4307d49e98f725aa5be5ab27a.webp","category":"教育","type":"应用","releaseDate":1766554535000,"relativePath":"教育/新博少儿.json","downCount":1078},{"name":"定时截屏助手","icon":"https://appimg-drcn.dbankcdn.com/application/icon144/phone/367221b923c44e9b93cc53056455fca7.webp","category":"工具","type":"应用","releaseDate":1766548982000,"relativePath":"工具/定时截屏助手.json","downCount":821},{"name":"安静书贴纸世界","icon":"https://appimg-drcn.dbankcdn.com/application/icon144/phone/4df0cc48abfb48d28c73266dd41bde54.webp","category":"休闲益智","type":"游戏","releaseDate":1766541373000,"relativePath":"休闲益智/安静书贴纸世界.json","downCount":1063},{"name":"安静书贴纸世界","icon":"https://appimg-drcn.dbankcdn.com/application/icon144/phone/4df0cc48abfb48d28c73266dd41bde54.webp","category":"益智解谜","type":"游戏","releaseDate":1766541373000,"relativePath":"益智解谜/安静书贴纸世界.json","downCount":1261},{"name":"超级文件快传","icon":"https://appimg-drcn.dbankcdn.com/application/icon144/phone/d8ec80f1f11249e889f2261765063a4f.webp","category":"工具","type":"应用","releaseDate":1766540663000,"relativePath":"工具/超级文件快传.json","downCount":1013},{"name":"血压血糖时光","icon":"https://appimg-drcn.dbankcdn.com/application/icon144/phone/ef9dd4b53d3146b1996cb531e586f55b.webp","category":"工具","type":"应用","releaseDate":1766540039000,"relativePath":"工具/血压血糖时光.json","downCount":1089},{"name":"可编可算","icon":"https://appimg-drcn.dbankcdn.com/application/icon144/phone/2d164dff01bd4bbbb581e5cf8e005df0.webp","category":"工具","type":"应用","releaseDate":1766538347000,"relativePath":"工具/可编可算.json","downCount":2655},{"name":"兼职小鱼","icon":"https://appimg-drcn.dbankcdn.com/application/icon144/phone/2f959339886d411d9f10d8ec3ef1721c.webp","category":"商务","type":"应用","releaseDate":1766537530000,"relativePath":"商务/兼职小鱼.json","downCount":5307},{"name":"升级","icon":"https://appimg-drcn.dbankcdn.com/application/icon144/phone/e9b2a7a1d73044d5b53dffdb14cdfeb7.webp","category":"棋牌","type":"游戏","releaseDate":1766498474000,"relativePath":"棋牌/升级.json","downCount":25458},{"name":"升级","icon":"https://appimg-drcn.dbankcdn.com/application/icon144/phone/e9b2a7a1d73044d5b53dffdb14cdfeb7.webp","category":"棋牌桌游","type":"游戏","releaseDate":1766498474000,"relativePath":"棋牌桌游/升级.json","downCount":22347},{"name":"赫兹商旅","icon":"https://appimg-drcn.dbankcdn.com/application/icon144/phone/d93edbd5f7e9422c93d62b1c88f354f0.webp","category":"商务","type":"应用","releaseDate":1766490461000,"relativePath":"商务/赫兹商旅.json","downCount":17761},{"name":"快捷输入面板","icon":"https://appimg-drcn.dbankcdn.com/application/icon144/phone/1872b0ffc0ca409cbc09af4ba31f77c9.webp","category":"工具","type":"应用","releaseDate":1766488091000,"relativePath":"工具/快捷输入面板.json","downCount":837},{"name":"自动签到助手","icon":"https://appimg-drcn.dbankcdn.com/application/icon144/phone/4b2aa40f13c14cc9b194265c64197d44.webp","category":"工具","type":"应用","releaseDate":1766480878000,"relativePath":"工具/自动签到助手.json","downCount":968},{"name":"编程计算器","icon":"https://appimg-drcn.dbankcdn.com/application/icon144/phone/298d45bc2e724c83b113b77239713a73.webp","category":"工具","type":"应用","releaseDate":1766479950000,"relativePath":"工具/编程计算器.json","downCount":5932},{"name":"驾考科目一2026","icon":"https://appimg-drcn.dbankcdn.com/application/icon144/phone/ca68263902a14fad924acd96ee8d2e50.webp","category":"汽车","type":"应用","releaseDate":1766477044000,"relativePath":"汽车/驾考科目一2026.json","downCount":5526},{"name":"京东钱包","icon":"https://appimg-drcn.dbankcdn.com/application/icon144/phone/7e38d5f203f84e8393db8665dcd1de54.webp","category":"金融理财","type":"应用","releaseDate":1766475321000,"relativePath":"金融理财/京东钱包.json","downCount":16430},{"name":"刷新生活","icon":"https://appimg-drcn.dbankcdn.com/application/icon144/phone/d8105846cb0e484eab64862d21155b3d.webp","category":"金融理财","type":"应用","releaseDate":1766472502000,"relativePath":"金融理财/刷新生活.json","downCount":27547},{"name":"HiGit","icon":"https://appimg-drcn.dbankcdn.com/application/icon144/phone/927fca75b73745839ae063c4a363f499.webp","category":"工具","type":"应用","releaseDate":1766469521000,"relativePath":"工具/HiGit.json","downCount":1371},{"name":"快电","icon":"https://appimg-drcn.dbankcdn.com/application/icon144/phone/6695a6aee0dd4a2e9d6bcd6136aa5916.webp","category":"汽车","type":"应用","releaseDate":1766459951000,"relativePath":"汽车/快电.json","downCount":74794},{"name":"MINI","icon":"https://appimg-drcn.dbankcdn.com/application/icon144/phone/71c4fdb4da694d2d94b9a32efef2332f.webp","category":"汽车","type":"应用","releaseDate":1766455206000,"relativePath":"汽车/MINI.json","downCount":18860},{"name":"My BMW","icon":"https://appimg-drcn.dbankcdn.com/application/icon144/phone/6eedf9b87ead446c924775ec0e0e9f37.webp","category":"汽车","type":"应用","releaseDate":1766455206000,"relativePath":"汽车/My BMW.json","downCount":573483},{"name":"修勾地铁逃生2","icon":"https://appimg-drcn.dbankcdn.com/application/icon144/phone/839b43c77ff74010be2edc3a908e2dac.webp","category":"休闲","type":"游戏","releaseDate":1766453839000,"relativePath":"休闲/修勾地铁逃生2.json","downCount":37548},{"name":"修勾地铁逃生2","icon":"https://appimg-drcn.dbankcdn.com/application/icon144/phone/839b43c77ff74010be2edc3a908e2dac.webp","category":"休闲益智","type":"游戏","releaseDate":1766453839000,"relativePath":"休闲益智/修勾地铁逃生2.json","downCount":32479},{"name":"修勾地铁逃生2","icon":"https://appimg-drcn.dbankcdn.com/application/icon144/phone/839b43c77ff74010be2edc3a908e2dac.webp","category":"动作射击","type":"游戏","releaseDate":1766453839000,"relativePath":"动作射击/修勾地铁逃生2.json","downCount":32145},{"name":"5G看家","icon":"https://appimg-drcn.dbankcdn.com/application/icon144/phone/3ebbdaf02bee4e9d9347cbb151f3745e.webp","category":"工具","type":"应用","releaseDate":1766452780000,"relativePath":"工具/5G看家.json","downCount":30421},{"name":"华闻e期","icon":"https://appimg-drcn.dbankcdn.com/application/icon144/phone/e0ce99a6466c40e9a38ffc75dac98e75.webp","category":"金融理财","type":"应用","releaseDate":1766406309000,"relativePath":"金融理财/华闻e期.json","downCount":3182},{"name":"凡亿教育","icon":"https://appimg-drcn.dbankcdn.com/application/icon144/phone/5c7120e27a59443387e39daad2424efb.webp","category":"教育","type":"应用","releaseDate":1766395362000,"relativePath":"教育/凡亿教育.json","downCount":946},{"name":"灵当CRM","icon":"https://appimg-drcn.dbankcdn.com/application/icon144/phone/3f378d9f460d470aa82e464840288ea3.webp","category":"商务","type":"应用","releaseDate":1766392475000,"relativePath":"商务/灵当CRM.json","downCount":1322},{"name":"华宝期权宝","icon":"https://appimg-drcn.dbankcdn.com/application/icon144/phone/1ed820da56654ff886f9b35b73142bca.webp","category":"金融理财","type":"应用","releaseDate":1766391016000,"relativePath":"金融理财/华宝期权宝.json","downCount":958},{"name":"好鹏友","icon":"https://appimg-drcn.dbankcdn.com/application/icon144/phone/5433e6193a3c427b8b08c2bbc85f69ed.webp","category":"商务","type":"应用","releaseDate":1766389820000,"relativePath":"商务/好鹏友.json","downCount":880},{"name":"牵心Pro","icon":"https://appimg-drcn.dbankcdn.com/application/icon144/phone/ada2bd73d8144e56b782e2b5e976a1b9.webp","category":"工具","type":"应用","releaseDate":1766388806000,"relativePath":"工具/牵心Pro.json","downCount":18989},{"name":"字母手势","icon":"https://appimg-drcn.dbankcdn.com/application/icon144/phone/7438074c375845fb889c0758c64ef770.webp","category":"工具","type":"应用","releaseDate":1766386110000,"relativePath":"工具/字母手势.json","downCount":752},{"name":"极简简历","icon":"https://appimg-drcn.dbankcdn.com/application/icon144/phone/4626d808a07248988e4dd26949652e31.webp","category":"工具","type":"应用","releaseDate":1766384366000,"relativePath":"工具/极简简历.json","downCount":8559},{"name":"iSecure Center","icon":"https://appimg-drcn.dbankcdn.com/application/icon144/phone/23daf53cea294f5591bdbf5aab06a766.webp","category":"工具","type":"应用","releaseDate":1766374241000,"relativePath":"工具/iSecure Center.json","downCount":35203},{"name":"货拉拉司机版","icon":"https://appimg-drcn.dbankcdn.com/application/icon144/phone/971d7d598d2f401ea5c73b21d2787f53.webp","category":"出行导航","type":"应用","releaseDate":1766368454000,"relativePath":"出行导航/货拉拉司机版.json","downCount":431426},{"name":"应用图标提取器","icon":"https://appimg-drcn.dbankcdn.com/application/icon144/phone/74ed6c8f04344b349e7baf9a84f19c2a.webp","category":"工具","type":"应用","releaseDate":1766368217000,"relativePath":"工具/应用图标提取器.json","downCount":685},{"name":"福村宝","icon":"https://appimg-drcn.dbankcdn.com/application/icon144/phone/b5278a2ba2414fd88716e6ae690154f3.webp","category":"生活服务","type":"应用","releaseDate":1766361616000,"relativePath":"生活服务/福村宝.json","downCount":73605},{"name":"照片水印","icon":"https://appimg-drcn.dbankcdn.com/application/icon144/phone/0589d13e26d2407f81aba7d75dde1572.webp","category":"拍摄美化","type":"应用","releaseDate":1766303531000,"relativePath":"拍摄美化/照片水印.json","downCount":2751},{"name":"Wteex","icon":"https://appimg-drcn.dbankcdn.com/application/icon144/phone/907e22641e3c44b88a62820a7cb10787.webp","category":"商务","type":"应用","releaseDate":1766218131000,"relativePath":"商务/Wteex.json","downCount":635},{"name":"电能管理","icon":"https://appimg-drcn.dbankcdn.com/application/icon144/phone/f3863b147e9946c98032243dee8c9b69.webp","category":"商务","type":"应用","releaseDate":1766217964000,"relativePath":"商务/电能管理.json","downCount":832},{"name":"猫制图","icon":"https://appimg-drcn.dbankcdn.com/application/icon144/phone/8cb432204fe841c584c1a6c34c7a3d5f.webp","category":"拍摄美化","type":"应用","releaseDate":1766200575000,"relativePath":"拍摄美化/猫制图.json","downCount":1415},{"name":"趣味数学","icon":"https://appimg-drcn.dbankcdn.com/application/icon144/phone/e0b06df7d4984bc9b5161eaef78fe2af.webp","category":"教育","type":"应用","releaseDate":1766195621000,"relativePath":"教育/趣味数学.json","downCount":5109},{"name":"新博少儿对弈平台","icon":"https://appimg-drcn.dbankcdn.com/application/icon144/phone/4f7a522ee8d84bcaa2fba4717192c785.webp","category":"教育","type":"应用","releaseDate":1766148931000,"relativePath":"教育/新博少儿对弈平台.json","downCount":22243},{"name":"掌上通","icon":"https://appimg-drcn.dbankcdn.com/application/icon144/phone/2e3ed1f6a83d4d98b483acc3e5b2c35d.webp","category":"工具","type":"应用","releaseDate":1766146674000,"relativePath":"工具/掌上通.json","downCount":834},{"name":"新博少儿国际象棋","icon":"https://appimg-drcn.dbankcdn.com/application/icon144/phone/e5434849fb454a8fb4c5b583ca59e89b.webp","category":"教育","type":"应用","releaseDate":1766145390000,"relativePath":"教育/新博少儿国际象棋.json","downCount":2550},{"name":"游泳教练聚题库","icon":"https://appimg-drcn.dbankcdn.com/application/icon144/phone/c2dda75007854f7889482931b451abcb.webp","category":"教育","type":"应用","releaseDate":1766141202000,"relativePath":"教育/游泳教练聚题库.json","downCount":678},{"name":"字体美化","icon":"https://appimg-drcn.dbankcdn.com/application/icon144/phone/5a7d7478049e4d55bfd1998db3b7ab5a.webp","category":"工具","type":"应用","releaseDate":1766138478000,"relativePath":"工具/字体美化.json","downCount":3214},{"name":"联想慧眼","icon":"https://appimg-drcn.dbankcdn.com/application/icon144/phone/fc8e289014cb4088b0e7020ad889b5e2.webp","category":"工具","type":"应用","releaseDate":1766137853000,"relativePath":"工具/联想慧眼.json","downCount":176784},{"name":"中成村镇银行","icon":"https://appimg-drcn.dbankcdn.com/application/icon144/phone/3e72007cdcc24c17bef770cdeb221e3c.webp","category":"金融理财","type":"应用","releaseDate":1766135425000,"relativePath":"金融理财/中成村镇银行.json","downCount":927},{"name":"跨平台剪切板","icon":"https://appimg-drcn.dbankcdn.com/application/icon144/phone/d45f484322694c738854708bef6acb48.webp","category":"工具","type":"应用","releaseDate":1766134739000,"relativePath":"工具/跨平台剪切板.json","downCount":998},{"name":"天肿云工作站","icon":"https://appimg-drcn.dbankcdn.com/application/icon144/phone/d7a2d2ff3cec499d885b94f0afdff923.webp","category":"医疗","type":"应用","releaseDate":1766134500000,"relativePath":"医疗/天肿云工作站.json","downCount":916},{"name":"投屏小助手","icon":"https://appimg-drcn.dbankcdn.com/application/icon144/phone/b5c241f9a711455fb47a8f9b3a0a6406.webp","category":"工具","type":"应用","releaseDate":1766134128000,"relativePath":"工具/投屏小助手.json","downCount":954},{"name":"智慧保护地","icon":"https://appimg-drcn.dbankcdn.com/application/icon144/phone/115685945c5a4961b8e32d9ce677f4b4.webp","category":"商务","type":"应用","releaseDate":1766133671000,"relativePath":"商务/智慧保护地.json","downCount":514},{"name":"王者象棋","icon":"https://appimg-drcn.dbankcdn.com/application/icon144/phone/dced2f53f18f4ec8a1d1a331d6486780.webp","category":"休闲娱乐","type":"应用","releaseDate":1766129019000,"relativePath":"休闲娱乐/王者象棋.json","downCount":10206},{"name":"联通视频彩铃","icon":"https://appimg-drcn.dbankcdn.com/application/icon144/phone/1c3eedb39ccd47d592d5adbc17035816.webp","category":"工具","type":"应用","releaseDate":1766125861000,"relativePath":"工具/联通视频彩铃.json","downCount":9195},{"name":"苏周到","icon":"https://appimg-drcn.dbankcdn.com/application/icon144/phone/1912f54c904d403c94d820fd83706de8.webp","category":"资讯","type":"应用","releaseDate":1766124986000,"relativePath":"资讯/苏周到.json","downCount":251973},{"name":"入党积极分子考试聚题库","icon":"https://appimg-drcn.dbankcdn.com/application/icon144/phone/782f712cd98240f3a02021afc67ddcf2.webp","category":"教育","type":"应用","releaseDate":1766123751000,"relativePath":"教育/入党积极分子考试聚题库.json","downCount":1634},{"name":"天天上门按摩","icon":"https://appimg-drcn.dbankcdn.com/application/icon144/phone/81fb9281e504488d91414dd1a2ad904b.webp","category":"运动健康","type":"应用","releaseDate":1766116505000,"relativePath":"运动健康/天天上门按摩.json","downCount":16339},{"name":"柠檬提醒日","icon":"https://appimg-drcn.dbankcdn.com/application/icon144/phone/142bc4e1942e49448651fb1a57685338.webp","category":"工具","type":"应用","releaseDate":1766113450000,"relativePath":"工具/柠檬提醒日.json","downCount":4039},{"name":"麦吉丽云课堂","icon":"https://appimg-drcn.dbankcdn.com/application/icon144/phone/1a3b4d18a3604663be0d7c2db0761a9a.webp","category":"教育","type":"应用","releaseDate":1766110527000,"relativePath":"教育/麦吉丽云课堂.json","downCount":1473},{"name":"神奇双击","icon":"https://appimg-drcn.dbankcdn.com/application/icon144/phone/572f21c31a5247daa18115976e678c8a.webp","category":"工具","type":"应用","releaseDate":1766109323000,"relativePath":"工具/神奇双击.json","downCount":3814},{"name":"商品出入库系统","icon":"https://appimg-drcn.dbankcdn.com/application/icon144/phone/8040232f7eaa497da1df286a11404c9f.webp","category":"工具","type":"应用","releaseDate":1766108969000,"relativePath":"工具/商品出入库系统.json","downCount":913},{"name":"助产士考试聚题库","icon":"https://appimg-drcn.dbankcdn.com/application/icon144/phone/abf0aa1a761b4bf4b62cd9749aece03a.webp","category":"教育","type":"应用","releaseDate":1766107757000,"relativePath":"教育/助产士考试聚题库.json","downCount":925},{"name":"收银员考试聚题库","icon":"https://appimg-drcn.dbankcdn.com/application/icon144/phone/8dc6fa10de994dc49f78c2ed452b7a9b.webp","category":"教育","type":"应用","releaseDate":1766061873000,"relativePath":"教育/收银员考试聚题库.json","downCount":891},{"name":"上海农机补贴","icon":"https://appimg-drcn.dbankcdn.com/application/icon144/phone/0ad80904a42945eba3739d2c7170cdac.webp","category":"工具","type":"应用","releaseDate":1766060715000,"relativePath":"工具/上海农机补贴.json","downCount":736},{"name":"UrlScheme助手","icon":"https://appimg-drcn.dbankcdn.com/application/icon144/phone/d8020e2817bc4083a74a41bc891e7804.webp","category":"工具","type":"应用","releaseDate":1766058518000,"relativePath":"工具/UrlScheme助手.json","downCount":1166},{"name":"PDF标注工具","icon":"https://appimg-drcn.dbankcdn.com/application/icon144/phone/5b50d08580eb4b45b59c0c830a34d354.webp","category":"工具","type":"应用","releaseDate":1766056941000,"relativePath":"工具/PDF标注工具.json","downCount":708},{"name":"单词通速记","icon":"https://appimg-drcn.dbankcdn.com/application/icon144/phone/e87eca62ba8549d0bbf2e8d3f07f58fe.webp","category":"教育","type":"应用","releaseDate":1766051570000,"relativePath":"教育/单词通速记.json","downCount":982},{"name":"健身教练资格证考试聚题库","icon":"https://appimg-drcn.dbankcdn.com/application/icon144/phone/c48294f508a24797ba55feb7b34a1ee9.webp","category":"教育","type":"应用","releaseDate":1766049889000,"relativePath":"教育/健身教练资格证考试聚题库.json","downCount":655},{"name":"徽行信用卡","icon":"https://appimg-drcn.dbankcdn.com/application/icon144/phone/c6dccd37c39142519be1f63847866371.webp","category":"金融理财","type":"应用","releaseDate":1766048263000,"relativePath":"金融理财/徽行信用卡.json","downCount":40238},{"name":"远光商旅","icon":"https://appimg-drcn.dbankcdn.com/application/icon144/phone/e7a317b4d6054bbcb8fce974c990bdc6.webp","category":"商务","type":"应用","releaseDate":1766046130000,"relativePath":"商务/远光商旅.json","downCount":613},{"name":"双击扫一扫","icon":"https://appimg-drcn.dbankcdn.com/application/icon144/phone/8649b16ffe0e40afac4b60fe6e7a145c.webp","category":"工具","type":"应用","releaseDate":1766045078000,"relativePath":"工具/双击扫一扫.json","downCount":835},{"name":"税务执法资格考试聚题库","icon":"https://appimg-drcn.dbankcdn.com/application/icon144/phone/4bf0dfb816fc45c88e33a1c166582502.webp","category":"教育","type":"应用","releaseDate":1766044337000,"relativePath":"教育/税务执法资格考试聚题库.json","downCount":798},{"name":"劳动保障协理员考试聚题库","icon":"https://appimg-drcn.dbankcdn.com/application/icon144/phone/7cc80330fd9941e0a843f036f1436029.webp","category":"教育","type":"应用","releaseDate":1766044251000,"relativePath":"教育/劳动保障协理员考试聚题库.json","downCount":867},{"name":"网格员考试聚题库","icon":"https://appimg-drcn.dbankcdn.com/application/icon144/phone/aab00a0098034057851e0f54110654b4.webp","category":"教育","type":"应用","releaseDate":1766043726000,"relativePath":"教育/网格员考试聚题库.json","downCount":506},{"name":"易订","icon":"https://appimg-drcn.dbankcdn.com/application/icon144/phone/4e8905017e38451d9bf5c04d30711603.webp","category":"美食","type":"应用","releaseDate":1766043169000,"relativePath":"美食/易订.json","downCount":6555},{"name":"AI公文写作","icon":"https://appimg-drcn.dbankcdn.com/application/icon144/phone/d23d0b8e263f40d6a0f548ea04161936.webp","category":"工具","type":"应用","releaseDate":1766041231000,"relativePath":"工具/AI公文写作.json","downCount":11522},{"name":"我的南京","icon":"https://appimg-drcn.dbankcdn.com/application/icon144/phone/0b8ebf3e1d8a4230b05667308b3231f9.webp","category":"生活服务","type":"应用","releaseDate":1766030257000,"relativePath":"生活服务/我的南京.json","downCount":395835},{"name":"星舰纪元","icon":"https://appimg-drcn.dbankcdn.com/application/icon144/phone/1d5328dec91e41abb05162eb396a7e88.webp","category":"策略","type":"游戏","releaseDate":1766029803000,"relativePath":"策略/星舰纪元.json","downCount":1678},{"name":"星舰纪元","icon":"https://appimg-drcn.dbankcdn.com/application/icon144/phone/1d5328dec91e41abb05162eb396a7e88.webp","category":"经营策略","type":"游戏","releaseDate":1766029803000,"relativePath":"经营策略/星舰纪元.json","downCount":1538},{"name":"网约配送员考试聚题库","icon":"https://appimg-drcn.dbankcdn.com/application/icon144/phone/62195a3377c94524adfd2999194eaeae.webp","category":"教育","type":"应用","releaseDate":1766028768000,"relativePath":"教育/网约配送员考试聚题库.json","downCount":890},{"name":"杏林学堂Pro","icon":"https://appimg-drcn.dbankcdn.com/application/icon144/phone/3e95863bbcd244ba83c618d0c6d46aaf.webp","category":"教育","type":"应用","releaseDate":1766027586000,"relativePath":"教育/杏林学堂Pro.json","downCount":6754},{"name":"望潮","icon":"https://appimg-drcn.dbankcdn.com/application/icon144/phone/15fd6a8a9b6b4cce84ca8eb612825ea8.webp","category":"新闻","type":"应用","releaseDate":1766024412000,"relativePath":"新闻/望潮.json","downCount":5354},{"name":"Med画图工具","icon":"https://appimg-drcn.dbankcdn.com/application/icon144/phone/53e7292796d14a708a3eb7ed1f06a09a.webp","category":"艺术与设计","type":"应用","releaseDate":1766022048000,"relativePath":"艺术与设计/Med画图工具.json","downCount":5616},{"name":"风铃天气","icon":"https://appimg-drcn.dbankcdn.com/application/icon144/phone/d67a5e581b1a49e69d2f54fe0b0f0215.webp","category":"生活服务","type":"应用","releaseDate":1766021015000,"relativePath":"生活服务/风铃天气.json","downCount":874},{"name":"军棋","icon":"https://appimg-drcn.dbankcdn.com/application/icon144/phone/8da39911b7a944c995c1a57c5f2b95da.webp","category":"棋牌","type":"游戏","releaseDate":1766019553000,"relativePath":"棋牌/军棋.json","downCount":60451},{"name":"军棋","icon":"https://appimg-drcn.dbankcdn.com/application/icon144/phone/8da39911b7a944c995c1a57c5f2b95da.webp","category":"棋牌桌游","type":"游戏","releaseDate":1766019553000,"relativePath":"棋牌桌游/军棋.json","downCount":54467},{"name":"门窗设计大师","icon":"https://appimg-drcn.dbankcdn.com/application/icon144/phone/a7aef71736914e49b86620fe281adbcf.webp","category":"商务","type":"应用","releaseDate":1765979363000,"relativePath":"商务/门窗设计大师.json","downCount":957},{"name":"味全智慧营运","icon":"https://appimg-drcn.dbankcdn.com/application/icon144/phone/9db0099c4fba43bda396289d9917e5bd.webp","category":"购物","type":"应用","releaseDate":1765973421000,"relativePath":"购物/味全智慧营运.json","downCount":842},{"name":"广西医保","icon":"https://appimg-drcn.dbankcdn.com/application/icon144/phone/43c06d5e35664f7f8e23c94899cf5346.webp","category":"医疗","type":"应用","releaseDate":1765972428000,"relativePath":"医疗/广西医保.json","downCount":16540},{"name":"文言文翻译字典","icon":"https://appimg-drcn.dbankcdn.com/application/icon144/phone/6df4691d9c0443efb5cbe8389686614d.webp","category":"教育","type":"应用","releaseDate":1765968971000,"relativePath":"教育/文言文翻译字典.json","downCount":920},{"name":"享记","icon":"https://appimg-drcn.dbankcdn.com/application/icon144/phone/773a8af19ec54f2ab3068355b52d9fd9.webp","category":"金融理财","type":"应用","releaseDate":1765968582000,"relativePath":"金融理财/享记.json","downCount":660},{"name":"知聊","icon":"https://appimg-drcn.dbankcdn.com/application/icon144/phone/aea696d073984c83aa58af5e93f98b67.webp","category":"社交","type":"应用","releaseDate":1765964106000,"relativePath":"社交/知聊.json","downCount":54691},{"name":"嘉实理财嘉","icon":"https://appimg-drcn.dbankcdn.com/application/icon144/phone/c88aa5ff95044846860b7453a58fbbeb.webp","category":"金融理财","type":"应用","releaseDate":1765960892000,"relativePath":"金融理财/嘉实理财嘉.json","downCount":11255},{"name":"体重小本","icon":"https://appimg-drcn.dbankcdn.com/application/icon144/phone/63d3c63b6fee4fe09cecd7abe7550ebf.webp","category":"运动健康","type":"应用","releaseDate":1765960028000,"relativePath":"运动健康/体重小本.json","downCount":63490},{"name":"国家电网安规考试聚题库","icon":"https://appimg-drcn.dbankcdn.com/application/icon144/phone/8770666943214156a9d0ddf4dbef6d4d.webp","category":"教育","type":"应用","releaseDate":1765959587000,"relativePath":"教育/国家电网安规考试聚题库.json","downCount":1777},{"name":"行政执法资格考试聚题库","icon":"https://appimg-drcn.dbankcdn.com/application/icon144/phone/f6cd31b72f744fa187d65dac5ca0908d.webp","category":"教育","type":"应用","releaseDate":1765958280000,"relativePath":"教育/行政执法资格考试聚题库.json","downCount":700},{"name":"电工考试聚题库","icon":"https://appimg-drcn.dbankcdn.com/application/icon144/phone/f3dbee26c1844477bd740f9f38591f20.webp","category":"教育","type":"应用","releaseDate":1765956066000,"relativePath":"教育/电工考试聚题库.json","downCount":2928},{"name":"阿尔法系统","icon":"https://appimg-drcn.dbankcdn.com/application/icon144/phone/9d2c559aa76847feb35d21fd2d22fe17.webp","category":"商务","type":"应用","releaseDate":1765954256000,"relativePath":"商务/阿尔法系统.json","downCount":713},{"name":"康熙字典","icon":"https://appimg-drcn.dbankcdn.com/application/icon144/phone/ad3d33d92b8445b1988c782c8c713aa4.webp","category":"教育","type":"应用","releaseDate":1765950725000,"relativePath":"教育/康熙字典.json","downCount":13497},{"name":"WiseCRM NT","icon":"https://appimg-drcn.dbankcdn.com/application/icon144/phone/0f18802fbfe3425f99487d3295588306.webp","category":"商务","type":"应用","releaseDate":1765935277000,"relativePath":"商务/WiseCRM NT.json","downCount":611},{"name":"AGA","icon":"https://appimg-drcn.dbankcdn.com/application/icon144/phone/99d999f741be4b80be1f2a266e49f333.webp","category":"金融理财","type":"应用","releaseDate":1765934886000,"relativePath":"金融理财/AGA.json","downCount":801},{"name":"记加班每天","icon":"https://appimg-drcn.dbankcdn.com/application/icon144/phone/cad569bc226c4ac8b5e773a93905d8c6.webp","category":"工具","type":"应用","releaseDate":1765894682000,"relativePath":"工具/记加班每天.json","downCount":652},{"name":"二狗英语","icon":"https://appimg-drcn.dbankcdn.com/application/icon144/phone/9c863a82d5a94506a880b6beeba9a51a.webp","category":"教育","type":"应用","releaseDate":1765894105000,"relativePath":"教育/二狗英语.json","downCount":681},{"name":"上财微门户","icon":"https://appimg-drcn.dbankcdn.com/application/icon144/phone/b025494e88cf4b219d01019086744485.webp","category":"教育","type":"应用","releaseDate":1765893159000,"relativePath":"教育/上财微门户.json","downCount":1332},{"name":"轻木鱼","icon":"https://appimg-drcn.dbankcdn.com/application/icon144/phone/3c7b0898bdc24b148657db313dacf224.webp","category":"运动健康","type":"应用","releaseDate":1765882862000,"relativePath":"运动健康/轻木鱼.json","downCount":104907},{"name":"爱湘潭","icon":"https://appimg-drcn.dbankcdn.com/application/icon144/phone/a58616f6e03947a2be8e62a778891f20.webp","category":"出行导航","type":"应用","releaseDate":1765877580000,"relativePath":"出行导航/爱湘潭.json","downCount":655},{"name":"vivo 官网","icon":"https://appimg-drcn.dbankcdn.com/application/icon144/phone/c78ca2c84273467184388999b1fe89ab.webp","category":"购物","type":"应用","releaseDate":1765869919000,"relativePath":"购物/vivo 官网.json","downCount":91788},{"name":"咕咕机","icon":"https://appimg-drcn.dbankcdn.com/application/icon144/phone/49cb645571a24175b5277ddc9f4caf59.webp","category":"工具","type":"应用","releaseDate":1765865688000,"relativePath":"工具/咕咕机.json","downCount":15578},{"name":"云栖日历","icon":"https://appimg-drcn.dbankcdn.com/application/icon144/phone/29ec7f0df7824451bbff103041d64780.webp","category":"工具","type":"应用","releaseDate":1765863918000,"relativePath":"工具/云栖日历.json","downCount":698},{"name":"简单提词器","icon":"https://appimg-drcn.dbankcdn.com/application/icon144/phone/d458d13ebc004001a10c1180b1688715.webp","category":"工具","type":"应用","releaseDate":1765857588000,"relativePath":"工具/简单提词器.json","downCount":679},{"name":"朋克养生","icon":"https://appimg-drcn.dbankcdn.com/application/icon144/phone/3b4a96b29f424545bb8afe34d88b392c.webp","category":"运动健康","type":"应用","releaseDate":1765800548000,"relativePath":"运动健康/朋克养生.json","downCount":1208},{"name":"卡帝手机控车","icon":"https://appimg-drcn.dbankcdn.com/application/icon144/phone/db318fb934c74ad9bff65f1dbe5ba6d3.webp","category":"工具","type":"应用","releaseDate":1765800501000,"relativePath":"工具/卡帝手机控车.json","downCount":3600},{"name":"青岛新区公交查询","icon":"https://appimg-drcn.dbankcdn.com/application/icon144/phone/7be25ff4857045d480b1b38e5d4f81d2.webp","category":"出行导航","type":"应用","releaseDate":1765796385000,"relativePath":"出行导航/青岛新区公交查询.json","downCount":11573},{"name":"医院挂号网","icon":"https://appimg-drcn.dbankcdn.com/application/icon144/phone/c2c07c66d97642de86c6233bf1d801d5.webp","category":"医疗","type":"应用","releaseDate":1765795968000,"relativePath":"医疗/医院挂号网.json","downCount":19955},{"name":"医考试","icon":"https://appimg-drcn.dbankcdn.com/application/icon144/phone/bbc1ee3c9ad34463b3c35efe14e989be.webp","category":"教育","type":"应用","releaseDate":1765795188000,"relativePath":"教育/医考试.json","downCount":911},{"name":"井唐","icon":"https://appimg-drcn.dbankcdn.com/application/icon144/phone/65019a6e992b44ac9a75d4a4e07fd6e6.webp","category":"工具","type":"应用","releaseDate":1765785128000,"relativePath":"工具/井唐.json","downCount":974},{"name":"字幕遮挡器","icon":"https://appimg-drcn.dbankcdn.com/application/icon144/phone/f2faf81cb78e4632b333fa066b8b419a.webp","category":"工具","type":"应用","releaseDate":1765785023000,"relativePath":"工具/字幕遮挡器.json","downCount":754},{"name":"随机冲突：土豆英雄","icon":"https://appimg-drcn.dbankcdn.com/application/icon144/phone/d87c86dc62054338a04b34173a2a820e.webp","category":"策略","type":"游戏","releaseDate":1765779256000,"relativePath":"策略/随机冲突：土豆英雄.json","downCount":4419},{"name":"随机冲突：土豆英雄","icon":"https://appimg-drcn.dbankcdn.com/application/icon144/phone/d87c86dc62054338a04b34173a2a820e.webp","category":"经营策略","type":"游戏","releaseDate":1765779256000,"relativePath":"经营策略/随机冲突：土豆英雄.json","downCount":4241},{"name":"北京广电","icon":"https://appimg-drcn.dbankcdn.com/application/icon144/phone/b615b705303d4356897198be3ffd05c6.webp","category":"商务","type":"应用","releaseDate":1765777794000,"relativePath":"商务/北京广电.json","downCount":1566},{"name":"魔术绘画","icon":"https://appimg-drcn.dbankcdn.com/application/icon144/phone/1243b3d8722b43f4ab54b4d0d8526588.webp","category":"工具","type":"应用","releaseDate":1765777783000,"relativePath":"工具/魔术绘画.json","downCount":884},{"name":"大连公交","icon":"https://appimg-drcn.dbankcdn.com/application/icon144/phone/bd8899fdd49b4aba81b54ac55639f830.webp","category":"出行导航","type":"应用","releaseDate":1765770926000,"relativePath":"出行导航/大连公交.json","downCount":23062},{"name":"吕梁公交","icon":"https://appimg-drcn.dbankcdn.com/application/icon144/phone/5241f18a7df44e6fbd10c966a7a038fe.webp","category":"出行导航","type":"应用","releaseDate":1765768321000,"relativePath":"出行导航/吕梁公交.json","downCount":687},{"name":"日程提醒管家","icon":"https://appimg-drcn.dbankcdn.com/application/icon144/phone/b193287be6214844a44f6cffd4f05439.webp","category":"工具","type":"应用","releaseDate":1765767925000,"relativePath":"工具/日程提醒管家.json","downCount":1205},{"name":"铁岭银行","icon":"https://appimg-drcn.dbankcdn.com/application/icon144/phone/9d49240ade99402894d8ce8b1166ec5c.webp","category":"金融理财","type":"应用","releaseDate":1765728006000,"relativePath":"金融理财/铁岭银行.json","downCount":5306},{"name":"正招标","icon":"https://appimg-drcn.dbankcdn.com/application/icon144/phone/4537cdc678dd412c8f461b1041ce00a8.webp","category":"资讯","type":"应用","releaseDate":1765703995000,"relativePath":"资讯/正招标.json","downCount":635},{"name":"保育员考试聚题库","icon":"https://appimg-drcn.dbankcdn.com/application/icon144/phone/800000b436ec413aa39cdb249188299e.webp","category":"教育","type":"应用","releaseDate":1765701001000,"relativePath":"教育/保育员考试聚题库.json","downCount":924},{"name":"划词翻译器","icon":"https://appimg-drcn.dbankcdn.com/application/icon144/phone/7a27fa1772d04ad99725db38ff78172c.webp","category":"工具","type":"应用","releaseDate":1765630415000,"relativePath":"工具/划词翻译器.json","downCount":957},{"name":"柒号色卡","icon":"https://appimg-drcn.dbankcdn.com/application/icon144/phone/739a91d389624c6f9c2261b2ed92824c.webp","category":"工具","type":"应用","releaseDate":1765621970000,"relativePath":"工具/柒号色卡.json","downCount":1092},{"name":"ADB小工具","icon":"https://appimg-drcn.dbankcdn.com/application/icon144/phone/2fa5ed81fea94642b24721ee48e14ff0.webp","category":"工具","type":"应用","releaseDate":1765619542000,"relativePath":"工具/ADB小工具.json","downCount":1088},{"name":"职堆堆兼职","icon":"https://appimg-drcn.dbankcdn.com/application/icon144/phone/3470267c3ef44d558ff3cb466e3e417a.webp","category":"商务","type":"应用","releaseDate":1765607060000,"relativePath":"商务/职堆堆兼职.json","downCount":5288},{"name":"智慧川传","icon":"https://appimg-drcn.dbankcdn.com/application/icon144/phone/bb6e41d898534cbd9b691f7f4bdfd12c.webp","category":"教育","type":"应用","releaseDate":1765597684000,"relativePath":"教育/智慧川传.json","downCount":2597},{"name":"东城公交","icon":"https://appimg-drcn.dbankcdn.com/application/icon144/phone/fc79cf52b6b44dc589cf2b169e5e4607.webp","category":"出行导航","type":"应用","releaseDate":1765597158000,"relativePath":"出行导航/东城公交.json","downCount":2476},{"name":"水城通E游","icon":"https://appimg-drcn.dbankcdn.com/application/icon144/phone/7dd5d76e554c48638c6357e4984bad9f.webp","category":"出行导航","type":"应用","releaseDate":1765594553000,"relativePath":"出行导航/水城通E游.json","downCount":2785},{"name":"曲靖公交","icon":"https://appimg-drcn.dbankcdn.com/application/icon144/phone/66d5312a47b24637b0d2e92fcda6f129.webp","category":"出行导航","type":"应用","releaseDate":1765593859000,"relativePath":"出行导航/曲靖公交.json","downCount":6123},{"name":"爱璧山","icon":"https://appimg-drcn.dbankcdn.com/application/icon144/phone/4a3107f681ed426da3fd734ed7bb2ed2.webp","category":"新闻","type":"应用","releaseDate":1765593030000,"relativePath":"新闻/爱璧山.json","downCount":642},{"name":"水城通E行","icon":"https://appimg-drcn.dbankcdn.com/application/icon144/phone/fbef2b4c530d4cecbfd0b5075cfeaaa0.webp","category":"出行导航","type":"应用","releaseDate":1765592703000,"relativePath":"出行导航/水城通E行.json","downCount":4152},{"name":"浮动图片","icon":"https://appimg-drcn.dbankcdn.com/application/icon144/phone/5642702d611147eea76f133b865b9986.webp","category":"工具","type":"应用","releaseDate":1765591309000,"relativePath":"工具/浮动图片.json","downCount":943},{"name":"永川头条","icon":"https://appimg-drcn.dbankcdn.com/application/icon144/phone/e3fe3dc914bb4701adffc9d755f87e3d.webp","category":"新闻","type":"应用","releaseDate":1765589169000,"relativePath":"新闻/永川头条.json","downCount":924},{"name":"蜜蜂试卷-扫描全能王出品","icon":"https://appimg-drcn.dbankcdn.com/application/icon144/phone/23338ab44a8a4dc68c633bc995c4f259.webp","category":"工具","type":"应用","releaseDate":1765549992000,"relativePath":"工具/蜜蜂试卷-扫描全能王出品.json","downCount":77596},{"name":"翠翠秀山","icon":"https://appimg-drcn.dbankcdn.com/application/icon144/phone/1345cd6be82d43f49e9b470224ea90bb.webp","category":"新闻","type":"应用","releaseDate":1765545186000,"relativePath":"新闻/翠翠秀山.json","downCount":759},{"name":"圆通速递","icon":"https://appimg-drcn.dbankcdn.com/application/icon144/phone/e7e5f7b94e2743b78a4f38daccdf4ae3.webp","category":"工具","type":"应用","releaseDate":1765542451000,"relativePath":"工具/圆通速递.json","downCount":113502},{"name":"文字提取相机","icon":"https://appimg-drcn.dbankcdn.com/application/icon144/phone/6e1088d9063b4691804c1ba94a97c86c.webp","category":"工具","type":"应用","releaseDate":1765542202000,"relativePath":"工具/文字提取相机.json","downCount":915},{"name":"延安公交","icon":"https://appimg-drcn.dbankcdn.com/application/icon144/phone/5937bac54d8f4696afeccef5aa33ae08.webp","category":"出行导航","type":"应用","releaseDate":1765541729000,"relativePath":"出行导航/延安公交.json","downCount":14119},{"name":"今日合川","icon":"https://appimg-drcn.dbankcdn.com/application/icon144/phone/05b3cc619c384f3682164ccaa09bfd23.webp","category":"新闻","type":"应用","releaseDate":1765541440000,"relativePath":"新闻/今日合川.json","downCount":623},{"name":"手绘画册","icon":"https://appimg-drcn.dbankcdn.com/application/icon144/phone/498a1ad177d34715839284bfb6592617.webp","category":"工具","type":"应用","releaseDate":1765541339000,"relativePath":"工具/手绘画册.json","downCount":513},{"name":"朔州公交","icon":"https://appimg-drcn.dbankcdn.com/application/icon144/phone/ae3310cfbc2a4f20816a4a832c119e60.webp","category":"出行导航","type":"应用","releaseDate":1765539147000,"relativePath":"出行导航/朔州公交.json","downCount":939},{"name":"比特球云盘","icon":"https://appimg-drcn.dbankcdn.com/application/icon144/phone/76ede99100ec437b8994021dba314513.webp","category":"工具","type":"应用","releaseDate":1765533522000,"relativePath":"工具/比特球云盘.json","downCount":6488},{"name":"南湖声音","icon":"https://appimg-drcn.dbankcdn.com/application/icon144/phone/84cb3ee298b949109a5ebb496cecfa2b.webp","category":"新闻","type":"应用","releaseDate":1765532601000,"relativePath":"新闻/南湖声音.json","downCount":1027},{"name":"条形码批量生成","icon":"https://appimg-drcn.dbankcdn.com/application/icon144/phone/83a0c58344494172a0a7c032b0a601bc.webp","category":"商务","type":"应用","releaseDate":1765528774000,"relativePath":"商务/条形码批量生成.json","downCount":1312},{"name":"Files文件大师","icon":"https://appimg-drcn.dbankcdn.com/application/icon144/phone/48e24afbded84a46a1e8dc4abf83b1bf.webp","category":"工具","type":"应用","releaseDate":1765527563000,"relativePath":"工具/Files文件大师.json","downCount":6549},{"name":"文本替换助手","icon":"https://appimg-drcn.dbankcdn.com/application/icon144/phone/abd6200f82b34c9e832b4ce5a8dbc6a1.webp","category":"工具","type":"应用","releaseDate":1765525583000,"relativePath":"工具/文本替换助手.json","downCount":594},{"name":"天气预报网","icon":"https://appimg-drcn.dbankcdn.com/application/icon144/phone/da1a7e134395492caa7504b231a529ad.webp","category":"生活服务","type":"应用","releaseDate":1765525180000,"relativePath":"生活服务/天气预报网.json","downCount":61713},{"name":"天气预报大字版","icon":"https://appimg-drcn.dbankcdn.com/application/icon144/phone/ca43f6ec2cec4736a8fe398eecb06b91.webp","category":"生活服务","type":"应用","releaseDate":1765523848000,"relativePath":"生活服务/天气预报大字版.json","downCount":59071},{"name":"天气预报星","icon":"https://appimg-drcn.dbankcdn.com/application/icon144/phone/8b6840c7c426459e810eea1452059c25.webp","category":"生活服务","type":"应用","releaseDate":1765523492000,"relativePath":"生活服务/天气预报星.json","downCount":24177},{"name":"字体大全","icon":"https://appimg-drcn.dbankcdn.com/application/icon144/phone/08fc247eaace4762899df3db3e00dd36.webp","category":"工具","type":"应用","releaseDate":1765502603000,"relativePath":"工具/字体大全.json","downCount":5064},{"name":"社会消防安全教育培训管理系统","icon":"https://appimg-drcn.dbankcdn.com/application/icon144/phone/5cf385a65956429789d5c342a483c4a3.webp","category":"教育","type":"应用","releaseDate":1765459801000,"relativePath":"教育/社会消防安全教育培训管理系统.json","downCount":2803},{"name":"长安汽车金融","icon":"https://appimg-drcn.dbankcdn.com/application/icon144/phone/514ccb4f36c34d2fb96d16f151994833.webp","category":"金融理财","type":"应用","releaseDate":1765459435000,"relativePath":"金融理财/长安汽车金融.json","downCount":6391},{"name":"信惠乡村","icon":"https://appimg-drcn.dbankcdn.com/application/icon144/phone/bcaf88ea127d47bba4af3b370eeb267f.webp","category":"生活服务","type":"应用","releaseDate":1765458918000,"relativePath":"生活服务/信惠乡村.json","downCount":1882},{"name":"FishingFox","icon":"https://appimg-drcn.dbankcdn.com/application/icon144/phone/9e4eef2a23be4aa4acd309c4b5220397.webp","category":"工具","type":"应用","releaseDate":1765457893000,"relativePath":"工具/FishingFox.json","downCount":39785},{"name":"出差宝库","icon":"https://appimg-drcn.dbankcdn.com/application/icon144/phone/50817a702cda4bbdbc767f172479f7f1.webp","category":"旅游","type":"应用","releaseDate":1765452855000,"relativePath":"旅游/出差宝库.json","downCount":1855},{"name":"健客医生","icon":"https://appimg-drcn.dbankcdn.com/application/icon144/phone/c29f6be69ff8411d9304f4584149934d.webp","category":"医疗","type":"应用","releaseDate":1765452272000,"relativePath":"医疗/健客医生.json","downCount":9530},{"name":"老人简洁桌面","icon":"https://appimg-drcn.dbankcdn.com/application/icon144/phone/a5bab30dd8184e42b726ab39404b31ae.webp","category":"工具","type":"应用","releaseDate":1765451268000,"relativePath":"工具/老人简洁桌面.json","downCount":911},{"name":"O吧","icon":"https://appimg-drcn.dbankcdn.com/application/icon144/phone/ad6a155e73d1484c9b57d25b55f6e4dd.webp","category":"生活服务","type":"应用","releaseDate":1765450881000,"relativePath":"生活服务/O吧.json","downCount":891},{"name":"山航掌尚飞","icon":"https://appimg-drcn.dbankcdn.com/application/icon144/phone/529acee46c674a37bad2dde40598256a.webp","category":"出行导航","type":"应用","releaseDate":1765449835000,"relativePath":"出行导航/山航掌尚飞.json","downCount":68028},{"name":"智慧巡检","icon":"https://appimg-drcn.dbankcdn.com/application/icon144/phone/fa6d3f9cbf1d4e58afee43e92e9105ff.webp","category":"商务","type":"应用","releaseDate":1765444460000,"relativePath":"商务/智慧巡检.json","downCount":676},{"name":"时间控","icon":"https://appimg-drcn.dbankcdn.com/application/icon144/phone/7fb362c4243046d28f51c9680debe333.webp","category":"工具","type":"应用","releaseDate":1765439848000,"relativePath":"工具/时间控.json","downCount":971},{"name":"PPT生成专家","icon":"https://appimg-drcn.dbankcdn.com/application/icon144/phone/a2ae51f892ea44b4b5528c4cedeb59fe.webp","category":"工具","type":"应用","releaseDate":1765438283000,"relativePath":"工具/PPT生成专家.json","downCount":1884},{"name":"齐鲁壹点","icon":"https://appimg-drcn.dbankcdn.com/application/icon144/phone/eeaa3df203f749d89fa2b873f7d5ee9e.webp","category":"新闻","type":"应用","releaseDate":1765437093000,"relativePath":"新闻/齐鲁壹点.json","downCount":3665},{"name":"遮天：凡尘一叶","icon":"https://appimg-drcn.dbankcdn.com/application/icon144/phone/4efdf0f404cc4b82a4c706430e11a587.webp","category":"卡牌","type":"游戏","releaseDate":1765436195000,"relativePath":"卡牌/遮天：凡尘一叶.json","downCount":8789},{"name":"遮天：凡尘一叶","icon":"https://appimg-drcn.dbankcdn.com/application/icon144/phone/4efdf0f404cc4b82a4c706430e11a587.webp","category":"角色扮演","type":"游戏","releaseDate":1765436195000,"relativePath":"角色扮演/遮天：凡尘一叶.json","downCount":8392},{"name":"移动白条","icon":"https://appimg-drcn.dbankcdn.com/application/icon144/phone/ee2e90e897804efe968d8757e3f9926d.webp","category":"金融理财","type":"应用","releaseDate":1765434103000,"relativePath":"金融理财/移动白条.json","downCount":8993},{"name":"视唱练耳","icon":"https://appimg-drcn.dbankcdn.com/application/icon144/phone/469645e2b28e4aefac528449432ab322.webp","category":"音乐","type":"应用","releaseDate":1765433601000,"relativePath":"音乐/视唱练耳.json","downCount":1283},{"name":"京东养车","icon":"https://appimg-drcn.dbankcdn.com/application/icon144/phone/370ec7b2d7d741858fdee2937e436c57.webp","category":"汽车","type":"应用","releaseDate":1765432761000,"relativePath":"汽车/京东养车.json","downCount":270595},{"name":"物流快递速查","icon":"https://appimg-drcn.dbankcdn.com/application/icon144/phone/2e92da5f1874420c85cf63c35ade112c.webp","category":"工具","type":"应用","releaseDate":1765431856000,"relativePath":"工具/物流快递速查.json","downCount":10472},{"name":"宠物翻译官","icon":"https://appimg-drcn.dbankcdn.com/application/icon144/phone/45ec1e2554274181852a88a68ed85dd9.webp","category":"工具","type":"应用","releaseDate":1765371070000,"relativePath":"工具/宠物翻译官.json","downCount":984},{"name":"工邦邦","icon":"https://appimg-drcn.dbankcdn.com/application/icon144/phone/ef2cba968f9449ce8f7d2e1d6e48c781.webp","category":"购物","type":"应用","releaseDate":1765370778000,"relativePath":"购物/工邦邦.json","downCount":1712},{"name":"Booking.com缤客","icon":"https://appimg-drcn.dbankcdn.com/application/icon144/phone/dcc2e55e19a34f95971d816794af6def.webp","category":"旅游","type":"应用","releaseDate":1765368709000,"relativePath":"旅游/Booking.com缤客.json","downCount":489095},{"name":"宝宝画廊","icon":"https://appimg-drcn.dbankcdn.com/application/icon144/phone/f03b4877179b4e1daa5eb2ecd308f0c9.webp","category":"工具","type":"应用","releaseDate":1765367250000,"relativePath":"工具/宝宝画廊.json","downCount":601},{"name":"广州挂号网","icon":"https://appimg-drcn.dbankcdn.com/application/icon144/phone/db63d86bf7d44e1d97da69abd8c05a8f.webp","category":"医疗","type":"应用","releaseDate":1765365071000,"relativePath":"医疗/广州挂号网.json","downCount":1506},{"name":"华泽微福","icon":"https://appimg-drcn.dbankcdn.com/application/icon144/phone/b53fe4592915435a9bbc5e2a5c310fe1.webp","category":"购物","type":"应用","releaseDate":1765357224000,"relativePath":"购物/华泽微福.json","downCount":9936},{"name":"甘肃医保服务平台","icon":"https://appimg-drcn.dbankcdn.com/application/icon144/phone/2ee27cf189d24c9b8af67419dfda0d78.webp","category":"生活服务","type":"应用","releaseDate":1765353776000,"relativePath":"生活服务/甘肃医保服务平台.json","downCount":24746},{"name":"进口机动车一致性证书验证系统","icon":"https://appimg-drcn.dbankcdn.com/application/icon144/phone/f0cb6d77485a488a91b6a78172dc7cf6.webp","category":"工具","type":"应用","releaseDate":1765352854000,"relativePath":"工具/进口机动车一致性证书验证系统.json","downCount":895},{"name":"看度新闻","icon":"https://appimg-drcn.dbankcdn.com/application/icon144/phone/26bc977bdf2143df9be7c7912f55ec34.webp","category":"新闻","type":"应用","releaseDate":1765349296000,"relativePath":"新闻/看度新闻.json","downCount":1889},{"name":"火山融","icon":"https://appimg-drcn.dbankcdn.com/application/icon144/phone/acc5d5b8909a46839a645563cbe9bfb5.webp","category":"金融理财","type":"应用","releaseDate":1765336387000,"relativePath":"金融理财/火山融.json","downCount":50433},{"name":"2345天气王","icon":"https://appimg-drcn.dbankcdn.com/application/icon144/phone/544c7a241663409080f44c6175f65032.webp","category":"生活服务","type":"应用","releaseDate":1765336127000,"relativePath":"生活服务/2345天气王.json","downCount":66883},{"name":"环保小智","icon":"https://appimg-drcn.dbankcdn.com/application/icon144/phone/011f86ec34444b0e9db3d5abb38ba4a5.webp","category":"工具","type":"应用","releaseDate":1765332131000,"relativePath":"工具/环保小智.json","downCount":5284},{"name":"手机动态壁纸","icon":"https://appimg-drcn.dbankcdn.com/application/icon144/phone/39b8686c220242f88693d8ef94a8ff56.webp","category":"主题","type":"应用","releaseDate":1765285722000,"relativePath":"主题/手机动态壁纸.json","downCount":29579},{"name":"山海志异","icon":"https://appimg-drcn.dbankcdn.com/application/icon144/phone/82a37ffc6d5b4af2b5d51f3d980692f9.webp","category":"角色扮演","type":"游戏","releaseDate":1765280104000,"relativePath":"角色扮演/山海志异.json","downCount":2807},{"name":"智慧兴隆","icon":"https://appimg-drcn.dbankcdn.com/application/icon144/phone/6f537c10508b47869a27b5da3b75b12b.webp","category":"工具","type":"应用","releaseDate":1765278440000,"relativePath":"工具/智慧兴隆.json","downCount":994},{"name":"钢琴谱大全","icon":"https://appimg-drcn.dbankcdn.com/application/icon144/phone/457c9bb715dd4b299bd7555aede823da.webp","category":"音乐","type":"应用","releaseDate":1765272616000,"relativePath":"音乐/钢琴谱大全.json","downCount":11675},{"name":"年化利率计算器","icon":"https://appimg-drcn.dbankcdn.com/application/icon144/phone/2cf61e3f8798449aa27f875cc3f97112.webp","category":"工具","type":"应用","releaseDate":1765267594000,"relativePath":"工具/年化利率计算器.json","downCount":3843},{"name":"理财有方","icon":"https://appimg-drcn.dbankcdn.com/application/icon144/phone/b8c8fd2479f24477a854f2dd5126acc4.webp","category":"金融理财","type":"应用","releaseDate":1765267444000,"relativePath":"金融理财/理财有方.json","downCount":690},{"name":"企业通","icon":"https://appimg-drcn.dbankcdn.com/application/icon144/phone/8091b8cd3d5e4c3bb70999b9b995987a.webp","category":"工具","type":"应用","releaseDate":1765265514000,"relativePath":"工具/企业通.json","downCount":116756},{"name":"搜才","icon":"https://appimg-drcn.dbankcdn.com/application/icon144/phone/b6ffc4415a9c492eb713d5cd3e10e468.webp","category":"商务","type":"应用","releaseDate":1765263893000,"relativePath":"商务/搜才.json","downCount":630},{"name":"微医","icon":"https://appimg-drcn.dbankcdn.com/application/icon144/phone/0e0722ce9cf848a3bb955883fa4585a2.webp","category":"医疗","type":"应用","releaseDate":1765261795000,"relativePath":"医疗/微医.json","downCount":118246},{"name":"广东南粤银行","icon":"https://appimg-drcn.dbankcdn.com/application/icon144/phone/793bc648347549b0a7552187d76aeeb1.webp","category":"金融理财","type":"应用","releaseDate":1765260854000,"relativePath":"金融理财/广东南粤银行.json","downCount":22491},{"name":"小木虫","icon":"https://appimg-drcn.dbankcdn.com/application/icon144/phone/c9119ebff8dd430680c41df8579df475.webp","category":"教育","type":"应用","releaseDate":1765249438000,"relativePath":"教育/小木虫.json","downCount":13874},{"name":"乐康守护","icon":"https://appimg-drcn.dbankcdn.com/application/icon144/phone/d5ee4bd37a194e12813d337caabfa78d.webp","category":"工具","type":"应用","releaseDate":1765195036000,"relativePath":"工具/乐康守护.json","downCount":40207},{"name":"我来数科","icon":"https://appimg-drcn.dbankcdn.com/application/icon144/phone/f413722e20194ab2b3f2b69cb00ef566.webp","category":"金融理财","type":"应用","releaseDate":1765190463000,"relativePath":"金融理财/我来数科.json","downCount":45707},{"name":"华泰期货期赢通","icon":"https://appimg-drcn.dbankcdn.com/application/icon144/phone/34dc834b2b924988a825e42d22565429.webp","category":"金融理财","type":"应用","releaseDate":1765178434000,"relativePath":"金融理财/华泰期货期赢通.json","downCount":13361},{"name":"嘉兴银行企业版","icon":"https://appimg-drcn.dbankcdn.com/application/icon144/phone/eb9846061b214d2f89d2d5f146119b13.webp","category":"金融理财","type":"应用","releaseDate":1765177120000,"relativePath":"金融理财/嘉兴银行企业版.json","downCount":701},{"name":"数字渝富","icon":"https://appimg-drcn.dbankcdn.com/application/icon144/phone/222f90cc42144afda512c422295f787c.webp","category":"效率","type":"应用","releaseDate":1765162166000,"relativePath":"效率/数字渝富.json","downCount":825},{"name":"都市漫游者","icon":"https://appimg-drcn.dbankcdn.com/application/icon144/phone/c2d48d43c5a94872af286190081d53f5.webp","category":"出行导航","type":"应用","releaseDate":1765155909000,"relativePath":"出行导航/都市漫游者.json","downCount":1945},{"name":"图片悬浮助手","icon":"https://appimg-drcn.dbankcdn.com/application/icon144/phone/0e2650f97646460fb63797de1b5c0838.webp","category":"工具","type":"应用","releaseDate":1765155669000,"relativePath":"工具/图片悬浮助手.json","downCount":738}]}