{"apps":8,"games":0,"list":[{"name":"豆包","icon":"https://appimg-drcn.dbankcdn.com/application/icon144/phone/5bd540aeaf3f4fc5b5578595682bb74e.webp","category":"工具","type":"应用","relativePath":"工具/豆包.json","currentDownCount":27221890,"previousDownCount":27092804,"delta":129086,"releaseDate":1774336933000},{"name":"智慧生活","icon":"https://appimg-drcn.dbankcdn.com/application/icon144/phone/83000b6e65bb48b5b4510eaeca8781f5.webp","category":"工具","type":"应用","relativePath":"工具/智慧生活.json","currentDownCount":46408633,"previousDownCount":46287796,"delta":120837,"releaseDate":1774613291000},{"name":"抖音","icon":"https://appimg-drcn.dbankcdn.com/application/icon144/phone/405f70be2fc94e5abf3045adba02eb4a.webp","category":"影视与直播","type":"应用","relativePath":"影视与直播/抖音.json","currentDownCount":47447411,"previousDownCount":47341927,"delta":105484,"releaseDate":1774947570000},{"name":"日历","icon":"https://appimg-drcn.dbankcdn.com/application/icon144/phone/d622a83a88cb4492a90ca820a5d5275e.webp","category":"效率","type":"应用","relativePath":"效率/日历.json","currentDownCount":50582017,"previousDownCount":50480391,"delta":101626,"releaseDate":1770622588000},{"name":"天气","icon":"https://appimg-drcn.dbankcdn.com/application/icon144/phone/1916506e3eb247d5bf00291ad6719ec1.webp","category":"生活服务","type":"应用","relativePath":"生活服务/天气.json","currentDownCount":50192651,"previousDownCount":50091122,"delta":101529,"releaseDate":1774870079000},{"name":"小艺","icon":"https://appimg-drcn.dbankcdn.com/application/icon144/phone/553e80087e714075bb363f50a23e37a7.webp","category":"工具","type":"应用","relativePath":"工具/小艺.json","currentDownCount":50621676,"previousDownCount":50520200,"delta":101476,"releaseDate":1775096997000},{"name":"京东","icon":"https://appimg-drcn.dbankcdn.com/application/icon144/phone/020e1220b15247ca93d1a78d4a273f2e.webp","category":"购物","type":"应用","relativePath":"购物/京东.json","currentDownCount":41246856,"previousDownCount":41145577,"delta":101279,"releaseDate":1775008752000},{"name":"查找设备","icon":"https://appimg-drcn.dbankcdn.com/application/icon144/phone/d1e232bff26045d9934f0459a16f28ec.webp","category":"工具","type":"应用","relativePath":"工具/查找设备.json","currentDownCount":46823863,"previousDownCount":46722886,"delta":100977,"releaseDate":1775134658000}]}