{"apps":3,"games":0,"list":[{"name":"繁花剧场","icon":"https://appimg-drcn.dbankcdn.com/application/icon144/phone/904c943db9cb4721ba2d3ab87dbf938b.webp","category":"影视与直播","type":"应用","relativePath":"影视与直播/繁花剧场.json","currentDownCount":2295660,"previousDownCount":2118025,"delta":177635,"releaseDate":1782267277000},{"name":"查找设备","icon":"https://appimg-drcn.dbankcdn.com/application/icon144/phone/c5254342d81f45af9025233c708f3d48.webp","category":"工具","type":"应用","relativePath":"工具/查找设备.json","currentDownCount":60237276,"previousDownCount":60073541,"delta":163735,"releaseDate":1778743142000},{"name":"千问","icon":"https://appimg-drcn.dbankcdn.com/application/icon144/phone/a1c8616d1e68477c90941c029ac18b86.webp","category":"工具","type":"应用","relativePath":"工具/千问.json","currentDownCount":11547418,"previousDownCount":11394976,"delta":152442,"releaseDate":1782268032000}]}